Workbook

Sheet Assumptions
A1: OFFICE INVESTMENT — VALUATION MODEL
A3: INPUTS (edit the yellow cells — everything else recalculates)
A5: Purchase price | B5: 4550000 | C5: What you paid
A6: Service charge per quarter | B6: 10000 | C6: Owner-paid
A7: Annual service charge | B7: =B6*4 | C7: =quarterly x 4
A8: Current lease year (passing) | B8: 2 | C8: 1-5; today (Jun 2026) = Year 2
A9: Agent commission rate | B9: 0.02 | C9: Market standard 2%
A10: VAT on commission | B10: 0.05 | C10: 5% VAT on the commission
A11: Passing rent (current year) | B11: =INDEX('Lease Schedule'!C5:C9,B8) | C11: Auto-selected from lease schedule
A12: NOI (net operating income) | B12: =B11-B7 | C12: =passing rent − annual service charge
A14: Net yield on cost | B14: =Assumptions!B12/B5 | C14: How good your purchase is

Sheet Lease Schedule
A1: LEASE SCHEDULE (May 2025 – May 2030, 5% annual escalation)
A4: Year | B4: Period | C4: Annual Rent | D4: Escalation
A5: 1 | B5: May 2025 – May 2026 | C5: 465992 | D5: —
A6: 2 | B6: May 2026 – May 2027 | C6: 489291.6 | D6: =C6/C5-1
A7: 3 | B7: May 2027 – May 2028 | C7: 513756.18 | D7: =C7/C6-1
A8: 4 | B8: May 2028 – May 2029 | C8: 539443.99 | D8: =C8/C7-1
A9: 5 | B9: May 2029 – May 2030 | C9: 566416.19 | D9: =C9/C8-1
B10: TOTAL | C10: =SUM(C5:C9)
B12: ⬑ Year 2 (gold) = current passing rent used in valuation

Sheet Valuation
A1: VALUATION — INCOME CAPITALISATION
A3: Value = Income ÷ Target Yield. Owner pays service charge, so NET column is the realistic basis.
A5: Target Yield | B5: Value on GROSS rent | C5: Value on NET (NOI) | D5: Gain vs purchase (net basis)
A6: 0.07 | B6: =Assumptions!B11/A6 | C6: =Assumptions!B12/A6 | D6: =C6-Assumptions!B5
A7: 0.075 | B7: =Assumptions!B11/A7 | C7: =Assumptions!B12/A7 | D7: =C7-Assumptions!B5
A8: 0.08 | B8: =Assumptions!B11/A8 | C8: =Assumptions!B12/A8 | D8: =C8-Assumptions!B5
A9: 0.085 | B9: =Assumptions!B11/A9 | C9: =Assumptions!B12/A9 | D9: =C9-Assumptions!B5
A10: 0.09 | B10: =Assumptions!B11/A10 | C10: =Assumptions!B12/A10 | D10: =C10-Assumptions!B5
A12: Recommendation
A13: List at: | B13: AED 6.4M – 6.7M
A14: Expect to settle: | B14: AED 5.9M – 6.3M
A16: Selling points: 5% annual escalation • secured income to May 2030 • low service charge (8% of rent)

Sheet Net Proceeds
A1: NET PROCEEDS (no mortgage • DLD 4% buyer-paid)
A3: Seller cost = agent commission 2% + 5% VAT. Edit sale-price cells (gold) for your own scenarios.
A5: Sale Price | B5: Agent Comm. +VAT | C5: DLD (buyer-paid, ref) | D5: Net to You | E5: Gain vs 4.55M
A6: 5900000 | B6: =A6*Assumptions!B9*(1+Assumptions!B10) | C6: =A6*0.04 | D6: =A6-B6 | E6: =D6-Assumptions!B5
A7: 6000000 | B7: =A7*Assumptions!B9*(1+Assumptions!B10) | C7: =A7*0.04 | D7: =A7-B7 | E7: =D7-Assumptions!B5
A8: 6300000 | B8: =A8*Assumptions!B9*(1+Assumptions!B10) | C8: =A8*0.04 | D8: =A8-B8 | E8: =D8-Assumptions!B5
A9: 6500000 | B9: =A9*Assumptions!B9*(1+Assumptions!B10) | C9: =A9*0.04 | D9: =A9-B9 | E9: =D9-Assumptions!B5
A10: 6700000 | B10: =A10*Assumptions!B9*(1+Assumptions!B10) | C10: =A10*0.04 | D10: =A10-B10 | E10: =D10-Assumptions!B5
A12: Note: DLD 4% transfer fee shown for reference only — normally paid by the buyer.
