Workbook

Sheet Summary
A1: PROPERTY VALUATION — SUMMARY
A2: =Inputs!B5&" · "&Inputs!B6&" · "&Inputs!B7
A4: THE PROPERTY | D4: HOW TO USE
A5: Your cost / total invested | B5: =Inputs!B14 | D5: 1. Go to the INPUTS tab and edit the gold cells for your property.
A6: Built-up area (sqft) | B6: =Inputs!B8
A7: Passing rent (if tenanted) | B7: =Inputs!B38 | D7: 2. Set 'Tenanted?' to Yes for rented units, No for vacant/owner-occupier.
A8: NOI | B8: =Inputs!B39
A9: Net yield on cost | B9: =Inputs!B40 | D9: 3. Tenanted → read the Income / DCF value. Vacant → read the Comparable value.
A11: WHAT IT'S WORTH | D11: 4. Net Proceeds shows your take-home after costs; Returns solves for a target price.
A12: Income – headline @ target yield | B12: =Valuation!B15
A13: Comparable (area × psf) | B13: =Valuation!B16 | D13: 5. Everything on every tab recalculates from Inputs automatically.
A14: DCF | B14: =DCF!B24
A16: INDICATIVE VALUE | B16: =IF(Inputs!B38=0,Inputs!B27,Inputs!B39/Inputs!B33) | D16: TIP
A17: (income basis if tenanted, else comparable) | D17: For tenanted property the buyer pays for the income stream, so a low purchase yield vs the market means upside. For vacant property, price per sqft from recent comparable sales rules.
A19: Estimates only — commission a RICS valuation before transacting. DLD 4% normally buyer-paid.

Sheet Portfolio
A1: PORTFOLIO ROLL-UP — one row per property
A2: Standalone tab (does NOT depend on the Inputs tab). Fill the GOLD input columns for each property; values & totals auto-calculate. Tenanted → income value; Vacant → comparable (area × psf).
A3: INPUTS (edit these) | M3: AUTO-CALCULATED
A4: Property | B4: Type | C4: Tenanted? | D4: Area sqft | E4: Cost (AED) | F4: Yr-1 Rent | G4: Esc % | H4: Cur Yr | I4: Term | J4: Ann. Service Chg | K4: AED/sqft | L4: Target Yld | M4: Passing Rent | N4: NOI | O4: Net Yld | P4: Income Value | Q4: Comparable | R4: Indicative Value | S4: Gain vs Cost
A5: Office – Business Bay | B5: Office | C5: Yes | D5: 1200 | E5: 4550000 | F5: 465992 | G5: 0.05 | H5: 2 | I5: 5 | J5: 40000 | K5: 4200 | L5: 0.08 | M5: =IF(C5="Yes",F5*(1+G5)^(H5-1),0) | N5: =IF(M5=0,0,M5-J5) | O5: =IF(E5>0,N5/E5,0) | P5: =IF(M5=0,"",N5/L5) | Q5: =IF(N(D5)*N(K5)=0,"",D5*K5) | R5: =IF(M5>0,N5/L5,IF(N(D5)*N(K5)=0,0,D5*K5)) | S5: =IF(R5=0,"",R5-E5)
M6: =IF(C6="Yes",F6*(1+G6)^(H6-1),0) | N6: =IF(M6=0,0,M6-J6) | O6: =IF(E6>0,N6/E6,0) | P6: =IF(M6=0,"",N6/L6) | Q6: =IF(N(D6)*N(K6)=0,"",D6*K6) | R6: =IF(M6>0,N6/L6,IF(N(D6)*N(K6)=0,0,D6*K6)) | S6: =IF(R6=0,"",R6-E6)
M7: =IF(C7="Yes",F7*(1+G7)^(H7-1),0) | N7: =IF(M7=0,0,M7-J7) | O7: =IF(E7>0,N7/E7,0) | P7: =IF(M7=0,"",N7/L7) | Q7: =IF(N(D7)*N(K7)=0,"",D7*K7) | R7: =IF(M7>0,N7/L7,IF(N(D7)*N(K7)=0,0,D7*K7)) | S7: =IF(R7=0,"",R7-E7)
M8: =IF(C8="Yes",F8*(1+G8)^(H8-1),0) | N8: =IF(M8=0,0,M8-J8) | O8: =IF(E8>0,N8/E8,0) | P8: =IF(M8=0,"",N8/L8) | Q8: =IF(N(D8)*N(K8)=0,"",D8*K8) | R8: =IF(M8>0,N8/L8,IF(N(D8)*N(K8)=0,0,D8*K8)) | S8: =IF(R8=0,"",R8-E8)
M9: =IF(C9="Yes",F9*(1+G9)^(H9-1),0) | N9: =IF(M9=0,0,M9-J9) | O9: =IF(E9>0,N9/E9,0) | P9: =IF(M9=0,"",N9/L9) | Q9: =IF(N(D9)*N(K9)=0,"",D9*K9) | R9: =IF(M9>0,N9/L9,IF(N(D9)*N(K9)=0,0,D9*K9)) | S9: =IF(R9=0,"",R9-E9)
M10: =IF(C10="Yes",F10*(1+G10)^(H10-1),0) | N10: =IF(M10=0,0,M10-J10) | O10: =IF(E10>0,N10/E10,0) | P10: =IF(M10=0,"",N10/L10) | Q10: =IF(N(D10)*N(K10)=0,"",D10*K10) | R10: =IF(M10>0,N10/L10,IF(N(D10)*N(K10)=0,0,D10*K10)) | S10: =IF(R10=0,"",R10-E10)
M11: =IF(C11="Yes",F11*(1+G11)^(H11-1),0) | N11: =IF(M11=0,0,M11-J11) | O11: =IF(E11>0,N11/E11,0) | P11: =IF(M11=0,"",N11/L11) | Q11: =IF(N(D11)*N(K11)=0,"",D11*K11) | R11: =IF(M11>0,N11/L11,IF(N(D11)*N(K11)=0,0,D11*K11)) | S11: =IF(R11=0,"",R11-E11)
M12: =IF(C12="Yes",F12*(1+G12)^(H12-1),0) | N12: =IF(M12=0,0,M12-J12) | O12: =IF(E12>0,N12/E12,0) | P12: =IF(M12=0,"",N12/L12) | Q12: =IF(N(D12)*N(K12)=0,"",D12*K12) | R12: =IF(M12>0,N12/L12,IF(N(D12)*N(K12)=0,0,D12*K12)) | S12: =IF(R12=0,"",R12-E12)
M13: =IF(C13="Yes",F13*(1+G13)^(H13-1),0) | N13: =IF(M13=0,0,M13-J13) | O13: =IF(E13>0,N13/E13,0) | P13: =IF(M13=0,"",N13/L13) | Q13: =IF(N(D13)*N(K13)=0,"",D13*K13) | R13: =IF(M13>0,N13/L13,IF(N(D13)*N(K13)=0,0,D13*K13)) | S13: =IF(R13=0,"",R13-E13)
M14: =IF(C14="Yes",F14*(1+G14)^(H14-1),0) | N14: =IF(M14=0,0,M14-J14) | O14: =IF(E14>0,N14/E14,0) | P14: =IF(M14=0,"",N14/L14) | Q14: =IF(N(D14)*N(K14)=0,"",D14*K14) | R14: =IF(M14>0,N14/L14,IF(N(D14)*N(K14)=0,0,D14*K14)) | S14: =IF(R14=0,"",R14-E14)
M15: =IF(C15="Yes",F15*(1+G15)^(H15-1),0) | N15: =IF(M15=0,0,M15-J15) | O15: =IF(E15>0,N15/E15,0) | P15: =IF(M15=0,"",N15/L15) | Q15: =IF(N(D15)*N(K15)=0,"",D15*K15) | R15: =IF(M15>0,N15/L15,IF(N(D15)*N(K15)=0,0,D15*K15)) | S15: =IF(R15=0,"",R15-E15)
M16: =IF(C16="Yes",F16*(1+G16)^(H16-1),0) | N16: =IF(M16=0,0,M16-J16) | O16: =IF(E16>0,N16/E16,0) | P16: =IF(M16=0,"",N16/L16) | Q16: =IF(N(D16)*N(K16)=0,"",D16*K16) | R16: =IF(M16>0,N16/L16,IF(N(D16)*N(K16)=0,0,D16*K16)) | S16: =IF(R16=0,"",R16-E16)
A17: PORTFOLIO TOTAL | D17: =SUM(D5:D16) | E17: =SUM(E5:E16) | N17: =SUM(N5:N16) | O17: =IF(SUM(E5:E16)>0,SUM(N5:N16)/SUM(E5:E16),0) | R17: =SUM(R5:R16) | S17: =SUM(S5:S16)
A19: Total invested | C19: Total value | E19: Total gain | G19: Total return | I19: Blended net yield
A20: =E17 | C20: =R17 | E20: =S17 | G20: =IF(E17>0,S17/E17,0) | I20: =O17
A22: Blended net yield = total NOI ÷ total invested. 'Indicative' uses income value for tenanted units, comparable (area × AED/sqft) for vacant. Gain ignores selling costs.

Sheet Inputs
A1: PROPERTY VALUATION — INPUTS
A2: Edit the GOLD cells. Blue cells auto-calculate. Works for any property — tenanted or vacant.
A4: A · PROPERTY DETAILS
A5: Property name / reference | B5: Office – Business Bay
A6: Property type | B6: Office | C6: Pick from dropdown
A7: Location / community | B7: Business Bay
A8: Built-up area (sqft) | B8: 1200 | C8: For price-per-sqft method
A9: Tenanted? | B9: Yes | C9: Yes = use income method; No = use comparable
A11: B · COSTS
A12: Purchase price / your cost | B12: 4550000
A13: Acquisition costs already paid | B13: 0 | C13: DLD 4% + agency, if you want total invested
A14: Total invested | B14: =B12+B13
A16: C · INCOME (fill only if tenanted)
A17: Lease start | B17: May 2025
A18: Lease term (years) | B18: 5 | C18: Up to 10
A19: Year-1 annual rent | B19: 465992
A20: Annual escalation % | B20: 0.05 | C20: 0% = flat rent
A21: Current lease year (passing) | B21: 2 | C21: Which year are you in now? (1-term)
A22: Service charge per quarter | B22: 10000 | C22: Owner-paid; 0 if tenant pays
A23: Annual service charge | B23: =B22*4
A25: D · MARKET / COMPARABLE (for vacant or cross-check)
A26: Market price per sqft | B26: 4200 | C26: From comparable sold prices
A27: Comparable value (area × psf) | B27: =B8*B26
A29: E · RATES & FEES (edit to taste)
A30: Agent commission on sale | B30: 0.02 | C30: Dubai standard 2%
A31: VAT on commission | B31: 0.05
A32: DLD transfer fee | B32: 0.04 | C32: Usually buyer-paid
A33: Target yield (headline value) | B33: 0.08 | C33: Drives the headline price
A34: DCF discount rate | B34: 0.09 | C34: Required return
A35: DCF exit cap rate | B35: 0.08 | C35: Resale yield at lease end
A37: DERIVED (auto)
A38: Passing rent (current year) | B38: =IF(B9="Yes",B19*(1+B20)^(B21-1),0)
A39: NOI (net operating income) | B39: =IF(B38=0,0,B38-B23)
A40: Net yield on your cost | B40: =IF(B12>0,B39/B12,0)

Sheet Income Schedule
A1: INCOME SCHEDULE (auto-built from Inputs)
A2: Rent auto-fills from Year-1 rent + escalation, up to the lease term. Type actual figures over a cell to override.
A4: Lease Year | B4: Annual Rent | C4: Net Rent | D4: Notes
A5: 1 | B5: =IF(AND(Inputs!$B$9="Yes",1<=Inputs!$B$18),Inputs!$B$19*(1+Inputs!$B$20)^(1-1),"") | C5: =IF(B5="","",B5-Inputs!$B$23) | D5: Year-1 base rent
A6: 2 | B6: =IF(AND(Inputs!$B$9="Yes",2<=Inputs!$B$18),Inputs!$B$19*(1+Inputs!$B$20)^(2-1),"") | C6: =IF(B6="","",B6-Inputs!$B$23)
A7: 3 | B7: =IF(AND(Inputs!$B$9="Yes",3<=Inputs!$B$18),Inputs!$B$19*(1+Inputs!$B$20)^(3-1),"") | C7: =IF(B7="","",B7-Inputs!$B$23)
A8: 4 | B8: =IF(AND(Inputs!$B$9="Yes",4<=Inputs!$B$18),Inputs!$B$19*(1+Inputs!$B$20)^(4-1),"") | C8: =IF(B8="","",B8-Inputs!$B$23)
A9: 5 | B9: =IF(AND(Inputs!$B$9="Yes",5<=Inputs!$B$18),Inputs!$B$19*(1+Inputs!$B$20)^(5-1),"") | C9: =IF(B9="","",B9-Inputs!$B$23)
A10: 6 | B10: =IF(AND(Inputs!$B$9="Yes",6<=Inputs!$B$18),Inputs!$B$19*(1+Inputs!$B$20)^(6-1),"") | C10: =IF(B10="","",B10-Inputs!$B$23)
A11: 7 | B11: =IF(AND(Inputs!$B$9="Yes",7<=Inputs!$B$18),Inputs!$B$19*(1+Inputs!$B$20)^(7-1),"") | C11: =IF(B11="","",B11-Inputs!$B$23)
A12: 8 | B12: =IF(AND(Inputs!$B$9="Yes",8<=Inputs!$B$18),Inputs!$B$19*(1+Inputs!$B$20)^(8-1),"") | C12: =IF(B12="","",B12-Inputs!$B$23)
A13: 9 | B13: =IF(AND(Inputs!$B$9="Yes",9<=Inputs!$B$18),Inputs!$B$19*(1+Inputs!$B$20)^(9-1),"") | C13: =IF(B13="","",B13-Inputs!$B$23)
A14: 10 | B14: =IF(AND(Inputs!$B$9="Yes",10<=Inputs!$B$18),Inputs!$B$19*(1+Inputs!$B$20)^(10-1),"") | C14: =IF(B14="","",B14-Inputs!$B$23)
A16: TOTAL | B16: =SUM(B5:B14) | C16: =SUM(C5:C14)

Sheet Valuation
A1: VALUATION — INCOME & COMPARABLE
A3: Tenanted → use INCOME method. Vacant / owner-occupier → use COMPARABLE. Both shown for cross-check.
A5: Target Yield | B5: Value on GROSS rent | C5: Value on NET (NOI) | D5: Gain vs cost (net)
A6: 0.06 | B6: =IF(Inputs!$B$38=0,"n/a",Inputs!$B$38/A6) | C6: =IF(Inputs!$B$38=0,"n/a",Inputs!$B$39/A6) | D6: =IF(Inputs!$B$38=0,"n/a",C6-Inputs!$B$12)
A7: 0.065 | B7: =IF(Inputs!$B$38=0,"n/a",Inputs!$B$38/A7) | C7: =IF(Inputs!$B$38=0,"n/a",Inputs!$B$39/A7) | D7: =IF(Inputs!$B$38=0,"n/a",C7-Inputs!$B$12)
A8: 0.07 | B8: =IF(Inputs!$B$38=0,"n/a",Inputs!$B$38/A8) | C8: =IF(Inputs!$B$38=0,"n/a",Inputs!$B$39/A8) | D8: =IF(Inputs!$B$38=0,"n/a",C8-Inputs!$B$12)
A9: 0.075 | B9: =IF(Inputs!$B$38=0,"n/a",Inputs!$B$38/A9) | C9: =IF(Inputs!$B$38=0,"n/a",Inputs!$B$39/A9) | D9: =IF(Inputs!$B$38=0,"n/a",C9-Inputs!$B$12)
A10: 0.08 | B10: =IF(Inputs!$B$38=0,"n/a",Inputs!$B$38/A10) | C10: =IF(Inputs!$B$38=0,"n/a",Inputs!$B$39/A10) | D10: =IF(Inputs!$B$38=0,"n/a",C10-Inputs!$B$12)
A11: 0.085 | B11: =IF(Inputs!$B$38=0,"n/a",Inputs!$B$38/A11) | C11: =IF(Inputs!$B$38=0,"n/a",Inputs!$B$39/A11) | D11: =IF(Inputs!$B$38=0,"n/a",C11-Inputs!$B$12)
A12: 0.09 | B12: =IF(Inputs!$B$38=0,"n/a",Inputs!$B$38/A12) | C12: =IF(Inputs!$B$38=0,"n/a",Inputs!$B$39/A12) | D12: =IF(Inputs!$B$38=0,"n/a",C12-Inputs!$B$12)
A13: 0.1 | B13: =IF(Inputs!$B$38=0,"n/a",Inputs!$B$38/A13) | C13: =IF(Inputs!$B$38=0,"n/a",Inputs!$B$39/A13) | D13: =IF(Inputs!$B$38=0,"n/a",C13-Inputs!$B$12)
A15: Headline value @ target yield | B15: =IF(Inputs!B38=0,"n/a",Inputs!B39/Inputs!B33)
A16: Comparable value (area × psf) | B16: =Inputs!B27

Sheet DCF
A1: DCF — remaining cashflows + reversion (tenanted only)
A4: Lease Yr | B4: Net Rent | C4: Period t | D4: Disc.Factor | E4: PV
A5: 1 | B5: ='Income Schedule'!C5 | C5: =1-Inputs!$B$21+1 | D5: =IF(OR(C5<1,B5=""),0,1/(1+Inputs!$B$34)^C5) | E5: =IF(B5="",0,B5*D5)
A6: 2 | B6: ='Income Schedule'!C6 | C6: =2-Inputs!$B$21+1 | D6: =IF(OR(C6<1,B6=""),0,1/(1+Inputs!$B$34)^C6) | E6: =IF(B6="",0,B6*D6)
A7: 3 | B7: ='Income Schedule'!C7 | C7: =3-Inputs!$B$21+1 | D7: =IF(OR(C7<1,B7=""),0,1/(1+Inputs!$B$34)^C7) | E7: =IF(B7="",0,B7*D7)
A8: 4 | B8: ='Income Schedule'!C8 | C8: =4-Inputs!$B$21+1 | D8: =IF(OR(C8<1,B8=""),0,1/(1+Inputs!$B$34)^C8) | E8: =IF(B8="",0,B8*D8)
A9: 5 | B9: ='Income Schedule'!C9 | C9: =5-Inputs!$B$21+1 | D9: =IF(OR(C9<1,B9=""),0,1/(1+Inputs!$B$34)^C9) | E9: =IF(B9="",0,B9*D9)
A10: 6 | B10: ='Income Schedule'!C10 | C10: =6-Inputs!$B$21+1 | D10: =IF(OR(C10<1,B10=""),0,1/(1+Inputs!$B$34)^C10) | E10: =IF(B10="",0,B10*D10)
A11: 7 | B11: ='Income Schedule'!C11 | C11: =7-Inputs!$B$21+1 | D11: =IF(OR(C11<1,B11=""),0,1/(1+Inputs!$B$34)^C11) | E11: =IF(B11="",0,B11*D11)
A12: 8 | B12: ='Income Schedule'!C12 | C12: =8-Inputs!$B$21+1 | D12: =IF(OR(C12<1,B12=""),0,1/(1+Inputs!$B$34)^C12) | E12: =IF(B12="",0,B12*D12)
A13: 9 | B13: ='Income Schedule'!C13 | C13: =9-Inputs!$B$21+1 | D13: =IF(OR(C13<1,B13=""),0,1/(1+Inputs!$B$34)^C13) | E13: =IF(B13="",0,B13*D13)
A14: 10 | B14: ='Income Schedule'!C14 | C14: =10-Inputs!$B$21+1 | D14: =IF(OR(C14<1,B14=""),0,1/(1+Inputs!$B$34)^C14) | E14: =IF(B14="",0,B14*D14)
D16: PV of income | E16: =SUM(E5:E14)
A18: REVERSION (resale at lease end)
A19: Final-year net rent | B19: =IF(Inputs!B38=0,0,INDEX('Income Schedule'!C5:C14,Inputs!B18))
A20: Gross reversion value | B20: =IF(B19=0,0,B19/Inputs!B35)
A21: Period at reversion | B21: =Inputs!B18-Inputs!B21+1
A22: PV of reversion | B22: =IF(B20=0,0,B20/(1+Inputs!B34)^B21)
A24: DCF VALUE | B24: =IF(Inputs!B38=0,"n/a (vacant)",E16+B22)

Sheet Net Proceeds
A1: NET PROCEEDS ON SALE
A3: Edit the gold sale-price cells. Costs use the rates from the Inputs tab.
A5: Sale Price | B5: Agent +VAT | C5: DLD (ref) | D5: Net to You | E5: Gain vs cost
A6: 3000000 | B6: =A6*Inputs!$B$30*(1+Inputs!$B$31) | C6: =A6*Inputs!$B$32 | D6: =A6-B6 | E6: =D6-Inputs!$B$12
A7: 4000000 | B7: =A7*Inputs!$B$30*(1+Inputs!$B$31) | C7: =A7*Inputs!$B$32 | D7: =A7-B7 | E7: =D7-Inputs!$B$12
A8: 5000000 | B8: =A8*Inputs!$B$30*(1+Inputs!$B$31) | C8: =A8*Inputs!$B$32 | D8: =A8-B8 | E8: =D8-Inputs!$B$12
A9: 6000000 | B9: =A9*Inputs!$B$30*(1+Inputs!$B$31) | C9: =A9*Inputs!$B$32 | D9: =A9-B9 | E9: =D9-Inputs!$B$12
A10: 7000000 | B10: =A10*Inputs!$B$30*(1+Inputs!$B$31) | C10: =A10*Inputs!$B$32 | D10: =A10-B10 | E10: =D10-Inputs!$B$12
A11: 8000000 | B11: =A11*Inputs!$B$30*(1+Inputs!$B$31) | C11: =A11*Inputs!$B$32 | D11: =A11-B11 | E11: =D11-Inputs!$B$12
A13: DLD transfer fee shown for reference — normally paid by the buyer.

Sheet Returns
A1: RETURNS & TARGET PRICE
A3: INPUTS
A4: Your cost | B4: =Inputs!B12
A5: Holding period (years) | B5: 1 | C5: From buy to sale
A6: Net rent collected while holding | B6: 449292 | C6: Sum of net rent received
A7: Selling cost rate (comm+VAT) | B7: =Inputs!B30*(1+Inputs!B31)
A8: TARGET annual return | B8: 0.15 | C8: Your goal, compounded on cost
A10: Required sale price for target
A11: Required total profit | B11: =B4*((1+B8)^B5-1)
A12: Required sale price | B12: =(B11+B4-B6)/(1-B7)
A14: SCENARIO TABLE
A15: Sale Price | B15: Selling Cost | C15: Capital Gain | D15: Total Profit | E15: Simple ROI | F15: Annualised
A16: 4000000 | B16: =A16*$B$7 | C16: =A16-$B$4 | D16: =A16-B16-$B$4+$B$6 | E16: =D16/$B$4 | F16: =(1+E16)^(1/$B$5)-1
A17: 5000000 | B17: =A17*$B$7 | C17: =A17-$B$4 | D17: =A17-B17-$B$4+$B$6 | E17: =D17/$B$4 | F17: =(1+E17)^(1/$B$5)-1
A18: 5500000 | B18: =A18*$B$7 | C18: =A18-$B$4 | D18: =A18-B18-$B$4+$B$6 | E18: =D18/$B$4 | F18: =(1+E18)^(1/$B$5)-1
A19: 6000000 | B19: =A19*$B$7 | C19: =A19-$B$4 | D19: =A19-B19-$B$4+$B$6 | E19: =D19/$B$4 | F19: =(1+E19)^(1/$B$5)-1
A20: 6500000 | B20: =A20*$B$7 | C20: =A20-$B$4 | D20: =A20-B20-$B$4+$B$6 | E20: =D20/$B$4 | F20: =(1+E20)^(1/$B$5)-1
A21: 7000000 | B21: =A21*$B$7 | C21: =A21-$B$4 | D21: =A21-B21-$B$4+$B$6 | E21: =D21/$B$4 | F21: =(1+E21)^(1/$B$5)-1
