Workbook

Sheet README
A1: ORIZURU HOLIDAY HOMES LLC — CAPEX & OPEX FINANCIAL MODEL
A2: Dubai, UAE | Trade Licence 1634278 | TRN 105507385000001 | All figures in AED
A4: WHAT IS IN THIS WORKBOOK
A5: Tab | B5: What it does
A6: Funding Summary | B6: START HERE. Total CAPEX, Year-1 OPEX, and the peak cash the business actually needs to fund — tied against the AED 200,000 shareholder capital.
A7: Financial Summary | B7: 5-year P&L, cash flow and returns: EBITDA, net profit, free cash flow, IRR, NPV, MOIC, payback, break-even portfolio size and IRR sensitivities. Year 1 links live to the monthly model; Years 2–5 are driven by the editable inputs in its section 1.
A8: Assumptions | B8: Every OPEX input at Low / Base / High. Set SCENARIO in cell B4 and the whole model re-cuts. Set cell B6 to choose which marketing option is adopted from Month 3.
A9: CAPEX Summary | B9: One-off setup spend rolled up by category.
A10: CAPEX Detail | B10: Every CAPEX line at Low / Base / High: formation & licensing, technology, brand, equipment, deposits.
A11: Unit Setup (1 Unit) | B11: Cost to bring ONE unit live, plus a x1 to x80 portfolio scaling reference.
A12: OPEX Summary | B12: Year-1 OPEX by category, key metrics, and the notes you should read before circulating.
A13: OPEX Monthly | B13: The engine. 12 months across, every cost line down. Edit the yellow unit-ramp row to change the growth path.
A14: Marketing Comparison | B14: Option 1 vs Option 2 head-to-head, break-even units, and what to measure before deciding in Month 3.
A15: AI Subscriptions | B15: AI stack broken out tool by tool. Feeds the AI line in the OPEX model.
A17: THE FOUR LEVERS THAT MOVE EVERYTHING
A18: 1. | B18: Assumptions!B4 — SCENARIO (Low / Base / High).
A19: 2. | B19: Assumptions!B6 — marketing option adopted from Month 3 (or 'Both' to keep running in parallel).
A20: 3. | B20: OPEX Monthly, yellow row — new units signed each month. Currently ramps to 80 units by Month 12, matching the Business Profile's 70–80 Year-1 target. Set every month to 0 except M1 = 1 for a single-unit view.
A21: 4. | B21: Assumptions column F — the active value of any single line. Override any input in its Low/Base/High cells.
A22: 5. | B22: Financial Summary sections 1 and 1b — unit counts for Years 2–5, inflation, headcount, exit multiple, discount rate and the fixed-cost step-up. These drive every return metric.
A24: MODEL BASIS — AS CONFIRMED
A25: • | B25: PURE MANAGEMENT / COMMISSION-ONLY. Orizuru does not master-lease. There is NO unit rent, no unit DEWA and no unit internet anywhere in this model — those sit with the property owner.
A26: • | B26: Unit setup CAPEX is sized for ONE unit. The scaling table on 'Unit Setup (1 Unit)' shows portfolio cost but is not added to the CAPEX total.
A27: • | B27: Directors draw NO salary.
A28: • | B28: Operations & service staff: AED 3,000/month per person, starting with 1 person and scaling with the portfolio via the 'live units per operations staff member' ratio on the Assumptions tab.
A29: • | B29: Both marketing options run in parallel for Months 1–2, then one is adopted.
A30: • | B30: The 2% per signed unit is an ONGOING trailing commission on that unit's monthly revenue, charged every month for as long as the unit is live — not a one-off signing bonus.
A31: • | B31: Figures supplied and used as-is: domain name 3 years AED 387; company stamp AED 137. Both are one-off, so they sit in CAPEX.
A32: • | B32: Shareholder capital is AED 200,000 as confirmed. NOTE: the Business Profile states AED 2,000,000 — the two must be reconciled before the pack goes to the bank. This model uses AED 200,000.
A33: • | B33: Nothing here is sized to the capital figure. Everything is built bottom-up from what the business needs, then compared against the capital available on 'Funding Summary'.
A35: COLOUR LEGEND
A36: Blue text | B36: Hardcoded input — edit freely.
A37: Yellow fill | B37: Key lever, or a figure supplied by management.
A38: Black text | B38: Formula. Do not overwrite.
A39: Green text | B39: Link to another tab in this workbook.
A41: WHAT IS DELIBERATELY EXCLUDED
A42: • | B42: OTA commission (Airbnb / Booking.com, 15–18%). Under a commission-only model this is deducted from gross booking revenue before the owner's split — it is not an Orizuru operating cost. Add it only if your management contracts make Orizuru bear it.
A43: • | B43: Tourism Dirham. Collected from the guest, remitted to DET. Pure pass-through.
A44: • | B44: Corporate Tax itself (9% above AED 375,000 taxable profit) — a tax on profit, not OPEX. The compliance and filing cost IS included.
A45: • | B45: Depreciation on the CAPEX. Non-cash; belongs in the P&L, not an OPEX cash budget.
A46: • | B46: Unit furnishing. Owner-funded under this model. The operating layer Orizuru does fund is in CAPEX.
A47: • | B47: Bank minimum balance. A blocked asset, not a cost — shown as a memo on 'CAPEX Detail'.

Sheet Funding Summary
A1: FUNDING SUMMARY — WHAT THE BUSINESS ACTUALLY NEEDS
A2: CAPEX and Year-1 OPEX combined. All figures AED. Base case unless the scenario is changed on 'Assumptions'.
A4: 1. CAPITAL EXPENDITURE — one-off
A5: Item | B5: Low | C5: Base | D5: High | E5: Comment
A6: Company setup (formation, tech, brand, equipment, deposits) | B6: ='CAPEX Detail'!G50 -> 60824 | C6: ='CAPEX Detail'!H50 -> 101824 | D6: ='CAPEX Detail'!I50 -> 166324 | E6: Scale-insensitive — the same whether you run 1 unit or 80.
A7: Unit setup — 1 unit | B7: ='Unit Setup (1 Unit)'!D17 -> 6105 | C7: ='Unit Setup (1 Unit)'!E17 -> 9152 | D7: ='Unit Setup (1 Unit)'!F17 -> 13640 | E7: One unit only, as instructed. Multiply on the 'Unit Setup' tab for portfolio scale.
A8: Contingency on company setup | B8: ='CAPEX Detail'!G52 -> 6082.4 | C8: ='CAPEX Detail'!H52 -> 10182.4 | D8: ='CAPEX Detail'!I52 -> 16632.4
A9: TOTAL CAPEX | B9: =SUM(B6:B8) -> 73011.4 | C9: =SUM(C6:C8) -> 121158.4 | D9: =SUM(D6:D8) -> 196596.4
A11: 2. OPERATING EXPENDITURE — Year 1
A12: Total OPEX — Year 1 | C12: ='OPEX Summary'!B14 -> 713738.01 | E12: Active scenario only. Change SCENARIO on 'Assumptions' to see Low / High.
A13: Monthly average OPEX | C13: =C12/12 -> 59478.168 | E13: Year-1 total divided by 12.
A14: Exit run-rate OPEX (Month 12) | C14: ='OPEX Monthly'!N87 -> 113117.82 | E14: The steady-state monthly cost you carry into Year 2.
A16: 3. YEAR-1 TRADING — does it cover itself?
A17: Units signed by Month 12 | C17: ='OPEX Monthly'!N8 -> 80 | E17: Against the Business Profile's 70–80 Year-1 target. Driven by the yellow ramp row on 'OPEX Monthly'.
A18: Gross booking revenue (guest spend across the portfolio) | C18: ='OPEX Monthly'!O11 -> 3755160 | E18: NOT Orizuru's revenue. This is the money flowing through the account — likely what the Business Profile's AED 2.5–4.5M turnover figure refers to.
A19: Orizuru revenue (management fees retained) | C19: ='OPEX Monthly'!O12 -> 751032 | E19: Orizuru's actual top line under the commission-only model. Agree with your accountant which of these two figures goes to the bank — they are very different numbers.
A20: Total OPEX — Year 1 | C20: =C12 -> 713738.01
A21: Operating surplus / (deficit), Year 1 | C21: =C19-C20 -> 37293.985 | E21: Before corporate tax, before depreciation, and before any director remuneration.
A22: OPEX as % of Orizuru revenue | C22: =IF(C19=0,0,C20/C19) -> 0.95034301 | E22: Above 100% means Year 1 runs at an operating loss — normal while a portfolio ramps from zero.
A24: 4. TOTAL FUNDING REQUIREMENT
A25: Peak cumulative operating cash deficit | C25: =MIN(0,MIN('OPEX Monthly'!C93:N93)) -> -76726.005 | E25: The worst the cumulative operating cash position ever gets during Year 1. THIS is the working capital to fund — not the annual OPEX figure.
A26: Total CAPEX | C26: =C9 -> 121158.4
A27: Safety buffer | B27: 0.2 | C27: =(ABS(C25)+C26)*B27 -> 39576.881 | E27: Cover for the ramp landing slower than planned. Edit the percentage in column B.
A28: TOTAL FUNDING REQUIRED | C28: =ABS(C25)+C26+C27 -> 237461.29
A29: Shareholder capital available | C29: 200000 | E29: AED 200,000 as confirmed. The Business Profile states AED 2,000,000 — reconcile before submission.
A30: Headroom / (shortfall) | C30: =C29-C28 -> -37461.286 | E30: Negative means the ramp above cannot be funded from AED 200,000. Fix it by slowing the unit ramp, taking the Low CAPEX case, or re-charging unit-level OPEX to owners — see note 6 below.
A32: 5. READ THIS BEFORE YOU CIRCULATE
A33: • STAFFING SCALES WITH THE PORTFOLIO. Headcount is no longer fixed at one person: it is driven by the 'live units per operations staff member' ratio on the Assumptions tab (35 in the Base case, floor of one person), so the team grows through Year 1 as units come live. Salary stays at the AED 3,000/month specified. That rate is low for Dubai even for an operations assistant — if hiring proves harder than expected, raise the salary input rather than cutting the ratio.
A34: • THE 2% IS MODELLED AS ONGOING. It applies to every live unit every month, indefinitely, as confirmed. By Month 12 it is one of the largest single lines in the model and it never stops growing with the portfolio. If a one-off signing bonus was intended, this needs re-cutting — over three years the difference is very large.
A35: • REVENUE RECOGNITION. The Business Profile projects AED 2.5–4.5M Year-1 turnover. Under pure commission-only, Orizuru's own revenue at 70–80 units is materially lower; the AED 2.5–4.5M is closer to gross booking value passing through the account. Settle which figure you are presenting before the KYC pack goes to the bank.
A36: • CAPEX IS SIZED FOR ONE UNIT, OPEX RAMPS TO 80. This is deliberate and as instructed, but the two tabs are not on the same basis. If you take the portfolio to 80 units, the unit-setup CAPEX scales with it — see the scaling table on 'Unit Setup (1 Unit)' and add it to the funding requirement above.
A37: • MOST UNIT-LEVEL OPEX IS RE-CHARGEABLE. Housekeeping, DET permit renewals and consumables are commonly billed to the owner or the guest. Set those assumptions to 0 if your management contracts pass them through — it changes the OPEX total substantially.
A38: • AT AED 200,000 THE BASE CASE DOES NOT FUND ITSELF. Base CAPEX (121,158) plus the peak operating cash deficit (76,726) plus a 20% buffer comes to 237,461 against 200,000 available — a shortfall of about 37,000. Two levers close it: (a) take the Low CAPEX case, deferring the full website build and brand spend until cash turns positive, which alone gets you to roughly 20,000 of headroom; (b) re-charge unit-level OPEX (housekeeping, DET permit renewals, consumables) to owners and guests, which is standard Dubai practice. Doing both leaves about 38,000 of headroom and is the recommended path.
A39: • DO NOT TRY TO FIX IT BY SLOWING THE RAMP. This is counter-intuitive but the model is unambiguous: cutting the ramp from 80 units to 46 by Month 12 makes the peak cash deficit WORSE, not better (119,632 vs 76,726). Fixed OPEX — office, licence, staff, technology — runs regardless, so a slower ramp simply means paying it for longer before revenue catches up. If capital is tight, cut CAPEX and re-charge OPEX; do not cut growth.

Sheet Financial Summary
A1: FINANCIAL SUMMARY — 5-YEAR P&L, CASH FLOW & RETURNS
A2: All figures AED. Year 1 links live to the monthly model; Years 2–5 are driven by the inputs in section 1.
A4: 1. DRIVERS — edit the blue cells to re-cut every number below
A5: Line item | B5: Year 1 | C5: Year 2 | D5: Year 3 | E5: Year 4 | F5: Year 5 | G5: Basis / note
A6: Units under management at year end | B6: ='OPEX Monthly'!N8 -> 80 | C6: 130 | D6: 180 | E6: 220 | F6: 250 | G6: Year 1 links to the monthly model. Years 2–5 are your growth plan — the single biggest lever here.
A7: Average live units during the year | B7: =AVERAGE('OPEX Monthly'!C9:N9) -> 30.5 | C7: =(B6+C6)/2 -> 105 | D7: =(C6+D6)/2 -> 155 | E7: =(D6+E6)/2 -> 200 | F7: =(E6+F6)/2 -> 235 | G7: Revenue is earned by units that are LIVE, not units signed. Year 1 averages the actual monthly ramp.
A8: Live unit-months in the year | B8: =SUM('OPEX Monthly'!C9:N9) -> 366 | C8: =C7*12 -> 1260 | D8: =D7*12 -> 1860 | E8: =E7*12 -> 2400 | F8: =F7*12 -> 2820 | G8: Drives every per-unit variable cost.
A9: Price inflation (ADR) | B9: =0 -> 0 | C9: 0.03 | D9: 0.03 | E9: 0.03 | F9: 0.03 | G9: Applied to ADR from Year 2. Dubai STR rates have run ahead of this; 3% is deliberately conservative.
A10: Cost inflation | B10: =0 -> 0 | C10: 0.04 | D10: 0.04 | E10: 0.04 | F10: 0.04 | G10: Applied to all fixed and per-unit costs from Year 2.
A11: Average Daily Rate | B11: =Assumptions!$F$11 -> 450 | C11: =B11*(1+C9) -> 463.5 | D11: =C11*(1+D9) -> 477.405 | E11: =D11*(1+E9) -> 491.72715 | F11: =E11*(1+F9) -> 506.47896 | G11: Year 1 from the Assumptions tab.
A12: Gross booking revenue per unit per month | B12: =B11*Assumptions!$F$12*Assumptions!$F$13 -> 10260 | C12: =C11*Assumptions!$F$12*Assumptions!$F$13 -> 10567.8 | D12: =D11*Assumptions!$F$12*Assumptions!$F$13 -> 10884.834 | E12: =E11*Assumptions!$F$12*Assumptions!$F$13 -> 11211.379 | F12: =F11*Assumptions!$F$12*Assumptions!$F$13 -> 11547.72 | G12: What the guest pays. NOT Orizuru revenue.
A13: Operations & service headcount (average) | B13: =AVERAGE('OPEX Monthly'!C10:N10) -> 1.5 | C13: =MAX(Assumptions!$F$19,ROUNDUP(C7/Assumptions!$F$20,0)) -> 3 | D13: =MAX(Assumptions!$F$19,ROUNDUP(D7/Assumptions!$F$20,0)) -> 5 | E13: =MAX(Assumptions!$F$19,ROUNDUP(E7/Assumptions!$F$20,0)) -> 6 | F13: =MAX(Assumptions!$F$19,ROUNDUP(F7/Assumptions!$F$20,0)) -> 7 | G13: Driven by the 'live units per operations staff member' ratio on the Assumptions tab, with a floor of one person. Year 1 is the average of the actual monthly ramp. Change the ratio there and headcount, staff cost and EBITDA all move together.
A14: Average salary per operations head (monthly) | B14: =Assumptions!$F$21 -> 3000 | C14: =B14*(1+C10) -> 3120 | D14: =C14*(1+D10) -> 3244.8 | E14: =D14*(1+E10) -> 3374.592 | F14: =E14*(1+F10) -> 3509.5757 | G14: Year 1 as specified by management.
A15: 1b. FINANCIAL INPUTS — used by the cash flow and returns sections below
A16: Input | B16: Value | G16: Basis / note
A17: Fixed-cost step-up with portfolio growth | B17: 0.4 | G17: Share of portfolio growth that flows into 'other fixed costs'. A business running 235 units does not carry the same office, marketing and admin base as one running 30. At 40%, a doubling of the portfolio raises fixed costs by 40%. Set to 0% to assume pure operating leverage — optimistic, and the reason unadjusted models show implausible margins.
A18: Share of unit-onboarding cost borne by Orizuru | B18: 0 | G18: SET TO 0% per the instruction that only ONE unit's setup sits in CAPEX — i.e. onboarding is re-charged to the owner. Raise it to see what self-funding the rollout costs. Sensitivity below.
A19: Working capital as % of revenue | B19: 0.05 | G19: Cash tied up in guest and OTA settlement timing.
A20: Discount rate (cost of equity) | B20: 0.2 | G20: 20% is a reasonable hurdle for an unlisted, pre-trading UAE SME. Lower it and NPV rises.
A21: Exit EBITDA multiple | B21: 4 | G21: Assumes a trade sale at the end of Year 5. 4x final-year EBITDA is typical for an asset-light property-management book of this size.
A22: Shareholder capital invested (Year 0) | B22: ='Funding Summary'!C29 -> 200000 | G22: Links to the Funding Summary.
A23: 2. INCOME STATEMENT (P&L)
A24: Line item | B24: Year 1 | C24: Year 2 | D24: Year 3 | E24: Year 4 | F24: Year 5 | G24: Basis / note
A25: Gross booking value handled (memo) | B25: ='OPEX Monthly'!O11 -> 3755160 | C25: =C7*C12*12 -> 13315428 | D25: =D7*D12*12 -> 20245791 | E25: =E7*E12*12 -> 26907310 | F25: =F7*F12*12 -> 32564572 | G25: MEMO ONLY — this is guest money flowing through the account, not revenue. Never present this as turnover.
A26: REVENUE — management fees retained | B26: ='OPEX Monthly'!O12 -> 751032 | C26: =C25*Assumptions!$F$15 -> 2663085.6 | D26: =D25*Assumptions!$F$15 -> 4049158.2 | E26: =E25*Assumptions!$F$15 -> 5381461.9 | F26: =F25*Assumptions!$F$15 -> 6512914.3 | G26: Orizuru's actual top line under the commission-only model.
A27: Variable costs
A28: Unit operations (permits, cleaning, consumables, maintenance, linen) | B28: ='OPEX Monthly'!O61 -> 196420 | C28: =C8*(Assumptions!$F$52/12+Assumptions!$F$53+Assumptions!$F$54+Assumptions!$F$55+Assumptions!$F$56)*(1+C10)^(1) -> 703248 | D28: =D8*(Assumptions!$F$52/12+Assumptions!$F$53+Assumptions!$F$54+Assumptions!$F$55+Assumptions!$F$56)*(1+D10)^(2) -> 1079653.1 | E28: =E8*(Assumptions!$F$52/12+Assumptions!$F$53+Assumptions!$F$54+Assumptions!$F$55+Assumptions!$F$56)*(1+E10)^(3) -> 1448824.8 | F28: =F8*(Assumptions!$F$52/12+Assumptions!$F$53+Assumptions!$F$54+Assumptions!$F$55+Assumptions!$F$56)*(1+F10)^(4) -> 1770463.9 | G28: Scales directly with the portfolio. Much of it is re-chargeable to owners — see the note at the foot of this tab.
A29: Unit technology (PMS, dynamic pricing, smart locks) | B29: ='OPEX Monthly'!C9*0+SUM('OPEX Monthly'!C9:N9)*(Assumptions!$F$43+Assumptions!$F$44+Assumptions!$F$45) -> 45750 | C29: =C8*(Assumptions!$F$43+Assumptions!$F$44+Assumptions!$F$45)*(1+C10)^(1) -> 163800 | D29: =D8*(Assumptions!$F$43+Assumptions!$F$44+Assumptions!$F$45)*(1+D10)^(2) -> 251472 | E29: =E8*(Assumptions!$F$43+Assumptions!$F$44+Assumptions!$F$45)*(1+E10)^(3) -> 337459.2 | F29: =F8*(Assumptions!$F$43+Assumptions!$F$44+Assumptions!$F$45)*(1+F10)^(4) -> 412375.14 | G29: Priced per property, so it scales one-for-one with units.
A30: Unit-acquisition commission (2%, ongoing) | B30: ='OPEX Monthly'!O42 -> 75103.2 | C30: =C25*Assumptions!$F$40 -> 266308.56 | D30: =D25*Assumptions!$F$40 -> 404915.82 | E30: =E25*Assumptions!$F$40 -> 538146.19 | F30: =F25*Assumptions!$F$40 -> 651291.43 | G30: Charged on every live unit every month, indefinitely. Grows in line with the portfolio and never stops.
A31: Total variable costs | B31: =B28+B29+B30 -> 317273.2 | C31: =C28+C29+C30 -> 1133356.6 | D31: =D28+D29+D30 -> 1736040.9 | E31: =E28+E29+E30 -> 2324430.2 | F31: =F28+F29+F30 -> 2834130.5
A32: GROSS PROFIT | B32: =B26-B31 -> 433758.8 | C32: =C26-C31 -> 1529729 | D32: =D26-D31 -> 2313117.3 | E32: =E26-E31 -> 3057031.7 | F32: =F26-F31 -> 3678783.8
A33: Gross margin | B33: =IF(B26=0,0,B32/B26) -> 0.57755036 | C33: =IF(C26=0,0,C32/C26) -> 0.57441978 | D33: =IF(D26=0,0,D32/D26) -> 0.57125881 | E33: =IF(E26=0,0,E32/E26) -> 0.56806714 | F33: =IF(F26=0,0,F32/F26) -> 0.56484449 | G33: Contribution left over after the costs that grow with the portfolio.
A34: Fixed operating costs
A35: Staff (salaries, visas, insurance, gratuity, WPS) | B35: ='OPEX Monthly'!O22 -> 64242 | C35: =C13*C14*12*($B$35/MAX(1,$B$13*$B$14*12)) -> 133623.36 | D35: =D13*D14*12*($B$35/MAX(1,$B$13*$B$14*12)) -> 231613.82 | E35: =E13*E14*12*($B$35/MAX(1,$B$13*$B$14*12)) -> 289054.05 | F35: =F13*F14*12*($B$35/MAX(1,$B$13*$B$14*12)) -> 350718.92 | G35: Headcount x salary x 12, grossed up by the same employment loading as Year 1 (visas, mandatory insurance, gratuity, WPS) — roughly 19% on top of salary. Directors remain unpaid throughout.
A36: All other fixed costs (marketing, technology, office, compliance, contingency) | B36: ='OPEX Summary'!B14-B28-B29-B30-B35 -> 332222.81 | C36: =B36*(1+C10)*(1+$B$17*IF(B7=0,0,C7/B7-1)) -> 683093.68 | D36: =C36*(1+D10)*(1+$B$17*IF(C7=0,0,D7/C7-1)) -> 845735.03 | E36: =D36*(1+E10)*(1+$B$17*IF(D7=0,0,E7/D7-1)) -> 981707.4 | F36: =E36*(1+F10)*(1+$B$17*IF(E7=0,0,F7/E7-1)) -> 1092444 | G36: Year 1 is derived so that this tab ties EXACTLY to total Year-1 OPEX on the monthly model. Years 2–5 grow with cost inflation PLUS a step-up for portfolio growth (driver in section 1b) — a bigger book needs a bigger office, more marketing and more admin.
A37: Total fixed costs | B37: =B35+B36 -> 396464.81 | C37: =C35+C36 -> 816717.04 | D37: =D35+D36 -> 1077348.9 | E37: =E35+E36 -> 1270761.4 | F37: =F35+F36 -> 1443162.9
A38: EBITDA | B38: =B32-B37 -> 37293.985 | C38: =C32-C37 -> 713012 | D38: =D32-D37 -> 1235768.5 | E38: =E32-E37 -> 1786270.3 | F38: =F32-F37 -> 2235620.9 | G38: Earnings before interest, tax, depreciation and amortisation. The headline operating profit measure.
A39: EBITDA margin | B39: =IF(B26=0,0,B38/B26) -> 0.049656986 | C39: =IF(C26=0,0,C38/C26) -> 0.26773905 | D39: =IF(D26=0,0,D38/D26) -> 0.30519144 | E39: =IF(E26=0,0,E38/E26) -> 0.3319303 | F39: =IF(F26=0,0,F38/F26) -> 0.34325968 | G39: Asset-light property management typically runs 20–35% at scale.
A40: Capital expenditure in year | B40: ='Funding Summary'!C9 -> 121158.4 | C40: =(C6-B6)*'Unit Setup (1 Unit)'!E17*$B$18 -> 0 | D40: =(D6-C6)*'Unit Setup (1 Unit)'!E17*$B$18 -> 0 | E40: =(E6-D6)*'Unit Setup (1 Unit)'!E17*$B$18 -> 0 | F40: =(F6-E6)*'Unit Setup (1 Unit)'!E17*$B$18 -> 0 | G40: Year 1 is the full CAPEX from the Funding Summary. Years 2–5 are unit-onboarding cost on NEW units only, scaled by the share Orizuru bears (driver in section 4).
A41: Depreciation & amortisation | B41: =B40/3 -> 40386.133 | C41: =SUM($B40:C40)/3 -> 40386.133 | D41: =SUM($B40:D40)/3 -> 40386.133 | E41: =SUM(C40:E40)/3 -> 0 | F41: =SUM(D40:F40)/3 -> 0 | G41: Straight line over 3 years. Non-cash — added back in the cash flow below.
A42: EBIT (operating profit) | B42: =B38-B41 -> -3092.1478 | C42: =C38-C41 -> 672625.87 | D42: =D38-D41 -> 1195382.3 | E42: =E38-E41 -> 1786270.3 | F42: =F38-F41 -> 2235620.9
A43: Profit before tax | B43: =B42 -> -3092.1478 | C43: =C42 -> 672625.87 | D43: =D42 -> 1195382.3 | E43: =E42 -> 1786270.3 | F43: =F42 -> 2235620.9 | G43: No debt assumed, so no interest charge. Add a finance cost line here if the company borrows.
A44: UAE Corporate Tax | B44: =-MAX(0,(B43-375000)*0.09) -> 0 | C44: =-MAX(0,(C43-375000)*0.09) -> -26786.328 | D44: =-MAX(0,(D43-375000)*0.09) -> -73834.409 | E44: =-MAX(0,(E43-375000)*0.09) -> -127014.32 | F44: =-MAX(0,(F43-375000)*0.09) -> -167455.88 | G44: 9% on taxable profit above the AED 375,000 threshold. Nil below it.
A45: NET PROFIT | B45: =B43+B44 -> -3092.1478 | C45: =C43+C44 -> 645839.54 | D45: =D43+D44 -> 1121547.9 | E45: =E43+E44 -> 1659255.9 | F45: =F43+F44 -> 2068165
A46: Net margin | B46: =IF(B26=0,0,B45/B26) -> -0.0041171985 | C46: =IF(C26=0,0,C45/C26) -> 0.2425155 | D46: =IF(D26=0,0,D45/D26) -> 0.27698298 | E46: =IF(E26=0,0,E45/E26) -> 0.3083281 | F46: =IF(F26=0,0,F45/F26) -> 0.31754832
A47: 3. CASH FLOW
A48: Line item | B48: Year 1 | C48: Year 2 | D48: Year 3 | E48: Year 4 | F48: Year 5 | G48: Basis / note
A49: EBITDA | B49: =B38 -> 37293.985 | C49: =C38 -> 713012 | D49: =D38 -> 1235768.5 | E49: =E38 -> 1786270.3 | F49: =F38 -> 2235620.9
A50: Corporate tax paid | B50: =B44 -> 0 | C50: =C44 -> -26786.328 | D50: =D44 -> -73834.409 | E50: =E44 -> -127014.32 | F50: =F44 -> -167455.88
A51: Capital expenditure | B51: =-B40 -> -121158.4 | C51: =-C40 -> 0 | D51: =-D40 -> 0 | E51: =-E40 -> 0 | F51: =-F40 -> 0
A52: Movement in working capital | B52: =-B26*$B$19 -> -37551.6 | C52: =-(C26-B26)*$B$19 -> -95602.68 | D52: =-(D26-C26)*$B$19 -> -69303.632 | E52: =-(E26-D26)*$B$19 -> -66615.184 | F52: =-(F26-E26)*$B$19 -> -56572.619 | G52: Guest and OTA settlement timing. Cash tied up grows as revenue grows.
A53: FREE CASH FLOW | B53: =B49+B50+B51+B52 -> -121416.01 | C53: =C49+C50+C51+C52 -> 590622.99 | D53: =D49+D50+D51+D52 -> 1092630.4 | E53: =E49+E50+E51+E52 -> 1592640.7 | F53: =F49+F50+F51+F52 -> 2011592.4
A54: Cumulative free cash flow | B54: =B53 -> -121416.01 | C54: =B54+C53 -> 469206.98 | D54: =C54+D53 -> 1561837.4 | E54: =D54+E53 -> 3154478.1 | F54: =E54+F53 -> 5166070.5
A55: Closing cash balance (capital + cumulative FCF) | B55: ='Funding Summary'!C29+B54 -> 78583.985 | C55: ='Funding Summary'!C29+C54 -> 669206.98 | D55: ='Funding Summary'!C29+D54 -> 1761837.4 | E55: ='Funding Summary'!C29+E54 -> 3354478.1 | F55: ='Funding Summary'!C29+F54 -> 5366070.5 | G55: If this goes negative in any year the plan is not fundable from AED 200,000 as it stands.
A56: 4. RETURNS & VALUATION
A57: Measure | B57: Value | G57: Basis / note
A58: Exit / terminal value at end of Year 5 | B58: =F38*B21 -> 8942483.5 | G58: Year-5 EBITDA multiplied by the exit multiple above.
A59: Investor cash flow
A60: Year | B60: Year 0 | C60: Year 1 | D60: Year 2 | E60: Year 3 | F60: Year 4 | G60: Year 5
A61: Net cash flow to shareholders | B61: =-B22 -> -200000 | C61: =B53 -> -121416.01 | D61: =C53 -> 590622.99 | E61: =D53 -> 1092630.4 | F61: =E53 -> 1592640.7 | G61: =F53+B58 -> 10954076 | I61: Year 0 is the capital injection. Year 5 includes the exit proceeds.
A63: IRR — internal rate of return | B63: =IRR(B61:G61) -> 1.6927249 | G63: The annualised return to shareholders across the 5 years including the exit. Compare against the discount rate above — anything meaningfully higher creates value.
A64: NPV at the discount rate | B64: =NPV(B20,C61:G61)+B61 -> 5911537.4 | G64: Positive NPV means the plan beats the hurdle rate.
A65: MOIC — money multiple | B65: =IF(B22=0,0,SUM(C61:G61)/B22) -> 70.54277 | G65: Total cash back divided by cash in.
A66: Payback — first year cumulative cash flow turns positive | B66: =IF(F54<0,"Beyond Year 5","Year "&(COUNTIF(B54:F54,"<0")+1)) -> Year 2 | G66: How long before the business has returned the cash it consumed.
A67: Revenue CAGR, Year 1 to Year 5 | B67: =IF(B26<=0,0,(F26/B26)^(1/4)-1) -> 0.71604721 | G67: Compound annual growth in management-fee revenue. Flattered by Year 1 being a part-year ramp from zero — the Year 2 to Year 5 rate below is the fairer measure.
A68: Revenue CAGR, Year 2 to Year 5 | B68: =IF(C26<=0,0,(F26/C26)^(1/3)-1) -> 0.34729722 | G68: Growth once the business is trading normally. This is the number to defend.
A69: EBITDA CAGR, Year 2 to Year 5 | B69: =IF(C38<=0,0,(F38/C38)^(1/3)-1) -> 0.46363832 | G69: Profit growth, stripping out the Year-1 ramp distortion.
A70: Return on equity (Year 5) | B70: =IF((B22+SUM(B45:E45))=0,0,F45/(B22+SUM(B45:E45))) -> 0.57075638 | G70: Year-5 net profit against closing shareholders' equity (capital plus retained earnings). More meaningful than measuring against the original AED 200,000 alone.
A71: 5. FINANCIAL HEALTH INDICATORS
A72: Line item | B72: Year 1 | C72: Year 2 | D72: Year 3 | E72: Year 4 | F72: Year 5 | G72: Basis / note
A73: Revenue per live unit (annual) | B73: =IF(B7=0,0,B26/B7) -> 24624 | C73: =IF(C7=0,0,C26/C7) -> 25362.72 | D73: =IF(D7=0,0,D26/D7) -> 26123.602 | E73: =IF(E7=0,0,E26/E7) -> 26907.31 | F73: =IF(F7=0,0,F26/F7) -> 27714.529 | G73: Should be broadly stable. A fall means discounting or weakening occupancy.
A74: Total cost per live unit (annual) | B74: =IF(B7=0,0,(B31+B37)/B7) -> 23401.246 | C74: =IF(C7=0,0,(C31+C37)/C7) -> 18572.129 | D74: =IF(D7=0,0,(D31+D37)/D7) -> 18150.902 | E74: =IF(E7=0,0,(E31+E37)/E7) -> 17975.958 | F74: =IF(F7=0,0,(F31+F37)/F7) -> 18201.249 | G74: Should FALL every year as fixed costs spread over more units. This is the whole scaling thesis.
A75: EBITDA per live unit (annual) | B75: =IF(B7=0,0,B38/B7) -> 1222.7536 | C75: =IF(C7=0,0,C38/C7) -> 6790.5905 | D75: =IF(D7=0,0,D38/D7) -> 7972.6997 | E75: =IF(E7=0,0,E38/E7) -> 8931.3513 | F75: =IF(F7=0,0,F38/F7) -> 9513.2803
A76: Contribution per unit (revenue less variable cost) | B76: =IF(B7=0,0,B32/B7) -> 14221.6 | C76: =IF(C7=0,0,C32/C7) -> 14568.848 | D76: =IF(D7=0,0,D32/D7) -> 14923.337 | E76: =IF(E7=0,0,E32/E7) -> 15285.159 | F76: =IF(F7=0,0,F32/F7) -> 15654.399 | G76: What each additional unit contributes towards fixed costs and profit.
A77: Break-even portfolio size (units) | B77: =IF(B76<=0,0,B37/B76) -> 27.877652 | C77: =IF(C76<=0,0,C37/C76) -> 56.059136 | D77: =IF(D76<=0,0,D37/D76) -> 72.19222 | E77: =IF(E76<=0,0,E37/E76) -> 83.136949 | F77: =IF(F76<=0,0,F37/F76) -> 92.188969 | G77: Units needed just to cover fixed costs. Compare against the average live units in row above — the gap is your margin of safety.
A78: Margin of safety (live units above break-even) | B78: =B7-B77 -> 2.6223481 | C78: =C7-C77 -> 48.940864 | D78: =D7-D77 -> 82.80778 | E78: =E7-E77 -> 116.86305 | F78: =F7-F77 -> 142.81103
A79: Fixed-cost coverage (gross profit / fixed costs) | B79: =IF(B37=0,0,B32/B37) -> 1.0940663 | C79: =IF(C37=0,0,C32/C37) -> 1.8730221 | D79: =IF(D37=0,0,D32/D37) -> 2.1470458 | E79: =IF(E37=0,0,E32/E37) -> 2.4056692 | F79: =IF(F37=0,0,F32/F37) -> 2.5491119 | G79: Below 1.0x the business is loss-making at EBITDA level.
A80: Cash runway at year-end (months of fixed cost) | B80: =IF(B37=0,0,B55/(B37/12)) -> 2.378541 | C80: =IF(C37=0,0,C55/(C37/12)) -> 9.832639 | D80: =IF(D37=0,0,D55/(D37/12)) -> 19.624144 | E80: =IF(E37=0,0,E55/(E37/12)) -> 31.676864 | F80: =IF(F37=0,0,F55/(F37/12)) -> 44.61925 | G80: How many months the closing cash balance would cover fixed costs with no revenue at all.
A81: 6. SENSITIVITY — what actually moves the IRR
A82: Case | B82: IRR | C82: NPV | G82: Comment
A83: Exit at 3.0x EBITDA | B83: =IRR(I83:N83) -> 1.6362816 | C83: =NPV(B20,J83:N83)+I83 -> 5013091.6 | G83: A weaker exit market. Note how much of the return depends on the sale, not the trading. | I83: =B61 -> -200000 | J83: =C61 -> -121416.01 | K83: =D61 -> 590622.99 | L83: =E61 -> 1092630.4 | M83: =F61 -> 1592640.7 | N83: =F53+F38*3.0 -> 8718455
A84: Exit at 4.0x EBITDA — base case | B84: =IRR(I84:N84) -> 1.6927249 | C84: =NPV(B20,J84:N84)+I84 -> 5911537.4 | I84: =B61 -> -200000 | J84: =C61 -> -121416.01 | K84: =D61 -> 590622.99 | L84: =E61 -> 1092630.4 | M84: =F61 -> 1592640.7 | N84: =F53+F38*4.0 -> 10954076
A85: Exit at 5.0x EBITDA | B85: =IRR(I85:N85) -> 1.7438389 | C85: =NPV(B20,J85:N85)+I85 -> 6809983.3 | G85: A strong strategic buyer. | I85: =B61 -> -200000 | J85: =C61 -> -121416.01 | K85: =D61 -> 590622.99 | L85: =E61 -> 1092630.4 | M85: =F61 -> 1592640.7 | N85: =F53+F38*5.0 -> 13189697
A86: No exit — operating cash only | B86: =IRR(I86:N86) -> 1.4145765 | C86: =NPV(B20,J86:N86)+I86 -> 2317753.9 | G86: The honest floor: what shareholders earn if the business is never sold. | I86: =B61 -> -200000 | J86: =C61 -> -121416.01 | K86: =D61 -> 590622.99 | L86: =E61 -> 1092630.4 | M86: =F61 -> 1592640.7 | N86: =F53+F38*0.0 -> 2011592.4
A87: Orizuru funds 0% of unit onboarding — base case | B87: =IRR(I87:N87) -> 1.6927249 | C87: =NPV(B20,J87:N87)+I87 -> 5911537.4 | G87: As instructed: onboarding re-charged to the owner. | I87: =B61 -> -200000 | J87: =C61-(C6-B6)*'Unit Setup (1 Unit)'!E17*(0.0-$B$18) -> -121416.01 | K87: =D61-(D6-C6)*'Unit Setup (1 Unit)'!E17*(0.0-$B$18) -> 590622.99 | L87: =E61-(E6-D6)*'Unit Setup (1 Unit)'!E17*(0.0-$B$18) -> 1092630.4 | M87: =F61-(F6-E6)*'Unit Setup (1 Unit)'!E17*(0.0-$B$18) -> 1592640.7 | N87: =G61-(F6-E6)*'Unit Setup (1 Unit)'!E17*(0.0-$B$18) -> 10954076
A88: Orizuru funds 50% of unit onboarding | B88: =IRR(I88:N88) -> 1.3205472 | C88: =NPV(B20,J88:N88)+I88 -> 5334682.5 | G88: A common commercial compromise where the operator shares setup cost to win the mandate. | I88: =B61 -> -200000 | J88: =C61-(C6-B6)*'Unit Setup (1 Unit)'!E17*(0.5-$B$18) -> -350216.01 | K88: =D61-(D6-C6)*'Unit Setup (1 Unit)'!E17*(0.5-$B$18) -> 361822.99 | L88: =E61-(E6-D6)*'Unit Setup (1 Unit)'!E17*(0.5-$B$18) -> 909590.41 | M88: =F61-(F6-E6)*'Unit Setup (1 Unit)'!E17*(0.5-$B$18) -> 1455360.7 | N88: =G61-(F6-E6)*'Unit Setup (1 Unit)'!E17*(0.5-$B$18) -> 10816796
A89: Orizuru funds 100% of unit onboarding | B89: =IRR(I89:N89) -> 1.0535876 | C89: =NPV(B20,J89:N89)+I89 -> 4757827.6 | G89: Self-funding the whole rollout. This is the scenario that breaks the AED 200,000 capital — check the closing cash balance if you go this way. | I89: =B61 -> -200000 | J89: =C61-(C6-B6)*'Unit Setup (1 Unit)'!E17*(1.0-$B$18) -> -579016.01 | K89: =D61-(D6-C6)*'Unit Setup (1 Unit)'!E17*(1.0-$B$18) -> 133022.99 | L89: =E61-(E6-D6)*'Unit Setup (1 Unit)'!E17*(1.0-$B$18) -> 726550.41 | M89: =F61-(F6-E6)*'Unit Setup (1 Unit)'!E17*(1.0-$B$18) -> 1318080.7 | N89: =G61-(F6-E6)*'Unit Setup (1 Unit)'!E17*(1.0-$B$18) -> 10679516
A91: 7. HOW TO READ THIS
A92: • YEAR 1 TIES EXACTLY TO THE MONTHLY MODEL. Revenue, staff, unit operations and commission all link straight to 'OPEX Monthly', and the residual fixed-cost line is derived so total Year-1 cost equals the monthly model to the dirham. Change anything on 'Assumptions' and Year 1 here moves with it.
A93: • YEARS 2–5 ARE A PLAN, NOT A FORECAST. They rest on the unit counts, inflation rates and headcount in section 1. Those are the numbers to argue about — everything below them is arithmetic.
A94: • THE IRR IS FLATTERED BY A SMALL CAPITAL BASE. Returns are measured against AED 200,000 of equity. A business that needs little capital and generates modest absolute profit will always show a high percentage return. Look at absolute EBITDA and the money multiple alongside the IRR, not the IRR alone.
A95: • MUCH OF THE RETURN SITS IN THE EXIT. Compare the base case against the 'no exit' row in section 6. If the gap is large, the plan depends on selling the business, not on operating it — which a lender will read very differently from an equity investor.
A96: • UNIT ONBOARDING IS THE HIDDEN CAPITAL RISK. This tab assumes owners fund unit setup, per instruction. If Orizuru ends up funding it to win mandates, the cash requirement rises sharply — section 6 quantifies it. Settle this in the management agreement before signing owners.
A97: • RE-CHARGEABLE COSTS ARE THE BIGGEST SINGLE LEVER. Housekeeping, DET permit renewals and consumables are all commonly billed to owners or guests. They sit in variable costs here. Re-charging them materially lifts EBITDA at no commercial cost — it is standard Dubai practice.
A98: • CORPORATE TAX BITES FROM THE YEAR PROFIT EXCEEDS AED 375,000. Below that the 9% rate does not apply. Watch the year the tax line first appears — that is when net profit starts diverging from EBITDA.

Sheet Assumptions
A1: OPEX ASSUMPTIONS — ORIZURU HOLIDAY HOMES LLC
A2: All figures AED unless stated. Blue = editable input. Yellow = figure supplied by management or a key lever.
A4: SCENARIO | B4: Base | C4: Change this cell to Low / Base / High. Every 'Active' figure below and the whole monthly model follow it. | J4: Low
A5: Scenario index | B5: =MATCH($B$4,$J$4:$J$6,0) -> 2 | J5: Base
A6: Option adopted from Month 3 | B6: Option 2 | C6: Both options run in Months 1–2 per management. From Month 3 the model keeps whichever you select here. Select 'Both' to keep running them in parallel all year. | J6: High
A7: Parallel-run months | B7: 2 | C7: Per management: run both marketing options together for the first 2 months to see which works.
A9: Assumption | B9: Unit | C9: Low | D9: Base | E9: High | F9: Active | G9: Source / note
A10: 1. REVENUE DRIVERS — needed to size the 2% commission, gateway fees and cost-to-revenue ratios
A11: Average Daily Rate (ADR) per unit | B11: AED/night | C11: 380 | D11: 450 | E11: 550 | F11: =INDEX(C11:E11,1,Assumptions!$B$5) -> 450 | G11: Premium 1BR short-term rental, Dubai. Drives the revenue base for the 2% marketing commission.
A12: Occupancy rate | B12: % | C12: 0.65 | D12: 0.75 | E12: 0.82 | F12: =INDEX(C12:E12,1,Assumptions!$B$5) -> 0.75 | G12: Dubai holiday-home market runs high; 75% is a realistic stabilised assumption.
A13: Nights per month | B13: nights | C13: 30.4 | D13: 30.4 | E13: 30.4 | F13: =INDEX(C13:E13,1,Assumptions!$B$5) -> 30.4 | G13: 365 / 12.
A14: Gross booking revenue per unit per month | B14: AED | C14: =C11*C12*C13 -> 7508.8 | D14: =D11*D12*D13 -> 10260 | E14: =E11*E12*E13 -> 13710.4 | F14: =INDEX(C14:E14,1,Assumptions!$B$5) -> 10260 | G14: Calculated. This is the GUEST's spend on that unit — not Orizuru's revenue.
A15: Management fee retained by Orizuru | B15: % of gross | C15: 0.15 | D15: 0.2 | E15: 0.25 | F15: =INDEX(C15:E15,1,Assumptions!$B$5) -> 0.2 | G15: Dubai holiday-home management contracts run 15–25%. This IS Orizuru's revenue under the commission-only model.
A16: Orizuru revenue per unit per month | B16: AED | C16: =C14*C15 -> 1126.32 | D16: =D14*D15 -> 2052 | E16: =E14*E15 -> 3427.6 | F16: =INDEX(C16:E16,1,Assumptions!$B$5) -> 2052 | G16: Calculated. Compare against the Business Profile's AED 2.5–4.5M turnover target — see the reconciliation note on the README tab.
A17: 2. STAFF — Dubai payroll
A18: Directors' salary | B18: AED/month | C18: 0 | D18: 0 | E18: 0 | F18: =INDEX(C18:E18,1,Assumptions!$B$5) -> 0 | G18: Per management: directors will NOT draw a salary. Note for the bank — this understates the true cost of running the business, since two directors are working unpaid.
A19: Operations & service staff — minimum headcount | B19: persons | C19: 1 | D19: 1 | E19: 1 | F19: =INDEX(C19:E19,1,Assumptions!$B$5) -> 1 | G19: Per management: the business starts with 1 person. Actual headcount rises with the portfolio — see the ratio below.
A20: Live units per operations staff member | B20: units/person | C20: 45 | D20: 35 | E20: 25 | F20: =INDEX(C20:E20,1,Assumptions!$B$5) -> 35 | G20: The staffing ratio. One person cannot run 80 units alone: check-ins, guest support, housekeeping coordination, maintenance and owner reporting across a portfolio spread over Dubai. 35 units per person is realistic with housekeeping outsourced. A LOWER number means MORE staff and higher cost — which is why the High-cost scenario uses 25.
A21: Operations & service staff — salary | B21: AED/month | C21: 3000 | D21: 3000 | E21: 3000 | F21: =INDEX(C21:E21,1,Assumptions!$B$5) -> 3000 | G21: Per management: AED 3,000/month.
A22: Staff visa, medical insurance & EID — monthly accrual per UAE employee | B22: AED/month | C22: 250 | D22: 380 | E22: 550 | F22: =INDEX(C22:E22,1,Assumptions!$B$5) -> 380 | G22: 2-year residence visa and mandatory Dubai health insurance spread monthly. Real cash cost even though it is billed in lumps.
A23: End-of-service gratuity accrual | B23: % of salary | C23: 0.058 | D23: 0.058 | E23: 0.058 | F23: =INDEX(C23:E23,1,Assumptions!$B$5) -> 0.058 | G23: UAE Labour Law: 21 days' basic pay per year of service for the first 5 years = 5.8% of salary. Legally payable — accrue it or it becomes a nasty surprise.
A24: WPS / payroll processing fee | B24: AED/employee/mo | C24: 8 | D24: 15 | E24: 25 | F24: =INDEX(C24:E24,1,Assumptions!$B$5) -> 15 | G24: Wage Protection System is mandatory for MOHRE-sponsored staff.
A25: 3. MARKETING OPTION 1 — FULLY ONLINE (4 hrs/day)
A26: Team size | B26: persons | C26: 2 | D26: 3 | E26: 4 | F26: =INDEX(C26:E26,1,Assumptions!$B$5) -> 3 | G26: Per management: 2–4 persons.
A27: Cost per person | B27: AED/month | C27: 500 | D27: 600 | E27: 700 | F27: =INDEX(C27:E27,1,Assumptions!$B$5) -> 600 | G27: Per management: AED 500–700 per person.
A28: Digital ads & owner lead generation | B28: AED/month | C28: 800 | D28: 1500 | E28: 2800 | F28: =INDEX(C28:E28,1,Assumptions!$B$5) -> 1500 | G28: A fully-online team without a paid lead flow will stall. This is the cost of feeding them owner leads.
A29: Outreach tooling, CRM & lead database | B29: AED/month | C29: 150 | D29: 280 | E29: 450 | F29: =INDEX(C29:E29,1,Assumptions!$B$5) -> 280 | G29: LinkedIn Sales Navigator / Property Finder lead access / CRM seats.
A30: Team coordination & QA time | B30: AED/month | C30: 0 | D30: 300 | E30: 600 | F30: =INDEX(C30:E30,1,Assumptions!$B$5) -> 300 | G30: Someone has to check the work. At 2–4 remote people this is light but not zero.
A31: 4. MARKETING OPTION 2 — REMOTE OFFICE OUTSIDE UAE (4 hrs/day)
A32: Team size | B32: persons | C32: 4 | D32: 5 | E32: 6 | F32: =INDEX(C32:E32,1,Assumptions!$B$5) -> 5 | G32: Per management: 4–6 persons.
A33: Cost per person | B33: AED/month | C33: 180 | D33: 240 | E33: 300 | F33: =INDEX(C33:E33,1,Assumptions!$B$5) -> 240 | G33: Per management: AED 180–300 per person.
A34: Coworking area rent | B34: AED/month | C34: 1350 | D34: 1425 | E34: 1500 | F34: =INDEX(C34:E34,1,Assumptions!$B$5) -> 1425 | G34: Per management: AED 1,350–1,500.
A35: Local internet, utilities & equipment | B35: AED/month | C35: 200 | D35: 350 | E35: 550 | F35: =INDEX(C35:E35,1,Assumptions!$B$5) -> 350 | G35: Not in the original brief but unavoidable — a physical room needs connectivity and machines.
A36: On-site supervisor / team lead | B36: AED/month | C36: 0 | D36: 500 | E36: 900 | F36: =INDEX(C36:E36,1,Assumptions!$B$5) -> 500 | G36: Not in the original brief. 4–6 people in a physical room with no supervisor will drift. Recommend keeping this.
A37: Digital ads & lead generation | B37: AED/month | C37: 400 | D37: 900 | E37: 1600 | F37: =INDEX(C37:E37,1,Assumptions!$B$5) -> 900 | G37: Lower than Option 1 — a larger team does more manual prospecting, so less paid volume is needed.
A38: Local compliance / entity or contractor arrangement | B38: AED/month | C38: 0 | D38: 400 | E38: 900 | F38: =INDEX(C38:E38,1,Assumptions!$B$5) -> 400 | G38: Not in the original brief. Engaging staff outside the UAE needs a compliant contracting route. Flagging it rather than pretending it is free.
A39: 5. UNIT-ACQUISITION COMMISSION — the 2% per management
A40: Trailing commission on each signed unit | B40: % | C40: 0.02 | D40: 0.02 | E40: 0.02 | F40: =INDEX(C40:E40,1,Assumptions!$B$5) -> 0.02 | G40: Per management: 2% for each unit signed, ONGOING on that unit's monthly revenue.
A41: Commission base | B41: — | C41: 1 | D41: 1 | E41: 1 | F41: =INDEX(C41:E41,1,Assumptions!$B$5) -> 1 | G41: 1 = 2% of the unit's GROSS booking revenue (i.e. c.10% of Orizuru's management fee on that unit). 2 = 2% of Orizuru's management fee only (far cheaper, far weaker incentive). Change the number to switch base.
A42: 6. TECHNOLOGY, PLATFORM & AI
A43: PMS / channel manager licence | B43: AED/unit/mo | C43: 55 | D43: 75 | E43: 95 | F43: =INDEX(C43:E43,1,Assumptions!$B$5) -> 75 | G43: Hostaway / Guesty style per-property pricing. Scales directly with the portfolio.
A44: Dynamic pricing tool | B44: AED/unit/mo | C44: 20 | D44: 32 | E44: 45 | F44: =INDEX(C44:E44,1,Assumptions!$B$5) -> 32 | G44: PriceLabs / Wheelhouse. Typically pays for itself many times over in RevPAR.
A45: Smart-lock / access platform | B45: AED/unit/mo | C45: 10 | D45: 18 | E45: 28 | F45: =INDEX(C45:E45,1,Assumptions!$B$5) -> 18 | G45: Recurring licence on the hardware installed at CAPEX.
A46: AI subscriptions | B46: AED/month | C46: 800 | D46: ='AI Subscriptions'!E16 -> 1318.4275 | E46: 3200 | F46: =INDEX(C46:E46,1,Assumptions!$B$5) -> 1318.4275 | G46: Per management (marketing/technology brief, item 5). Base links live to the 'AI Subscriptions' tab. Low = trimmed stack; High = full stack plus extra seats as the marketing team scales.
A47: Google Workspace / business email | B47: AED/month | C47: 90 | D47: 150 | E47: 260 | F47: =INDEX(C47:E47,1,Assumptions!$B$5) -> 150 | G47: Per-seat, scales with headcount.
A48: Accounting software (VAT-compliant) | B48: AED/month | C48: 90 | D48: 160 | E48: 280 | F48: =INDEX(C48:E48,1,Assumptions!$B$5) -> 160 | G48: Zoho Books / Xero. Mandatory once VAT-registered.
A49: Website hosting & direct booking engine | B49: AED/month | C49: 100 | D49: 190 | E49: 340 | F49: =INDEX(C49:E49,1,Assumptions!$B$5) -> 190 | G49: Recurring cost on the platform built at CAPEX.
A50: VoIP, WhatsApp Business API & guest support line | B50: AED/month | C50: 120 | D50: 230 | E50: 400 | F50: =INDEX(C50:E50,1,Assumptions!$B$5) -> 230 | G50: Required to deliver the 24/7 guest support promised in the Business Profile.
A51: 7. UNIT OPERATIONS — variable, per LIVE unit per month
A52: DET holiday-home permit renewal | B52: AED/unit/yr | C52: 1200 | D52: 1520 | E52: 1800 | F52: =INDEX(C52:E52,1,Assumptions!$B$5) -> 1520 | G52: Accrued monthly at 1/12. Re-chargeable to the owner in most contracts — if you re-charge, set this to 0.
A53: Housekeeping & laundry — net of guest recharge | B53: AED/unit/mo | C53: 0 | D53: 180 | E53: 420 | F53: =INDEX(C53:E53,1,Assumptions!$B$5) -> 180 | G53: Cleaning fees are normally charged to the guest and pass straight through. This line is the RESIDUAL Orizuru absorbs on unsold nights, owner stays and disputes. Genuinely 0 if you recharge everything.
A54: Guest consumables & amenities | B54: AED/unit/mo | C54: 55 | D54: 100 | E54: 170 | F54: =INDEX(C54:E54,1,Assumptions!$B$5) -> 100 | G54: Toiletries, coffee, water, welcome items. The Japanese-hospitality positioning makes this a brand cost, not a cost to strip out.
A55: Maintenance coordination & petty repairs | B55: AED/unit/mo | C55: 40 | D55: 90 | E55: 160 | F55: =INDEX(C55:E55,1,Assumptions!$B$5) -> 90 | G55: Orizuru's coordination cost. Major repairs are billed to the owner.
A56: Linen & towel replacement | B56: AED/unit/mo | C56: 20 | D56: 40 | E56: 70 | F56: =INDEX(C56:E56,1,Assumptions!$B$5) -> 40 | G56: Replacement cycle on the par stock bought at CAPEX. Real and routinely forgotten.
A57: 8. OFFICE & ADMINISTRATION — Dubai
A58: Office rent / registered address | B58: AED/month | C58: 1500 | D58: 2500 | E58: 4200 | F58: =INDEX(C58:E58,1,Assumptions!$B$5) -> 2500 | G58: Fronds Building – Office 02. Required to hold the trade licence.
A59: Office DEWA, internet & chiller | B59: AED/month | C59: 300 | D59: 520 | E59: 900 | F59: =INDEX(C59:E59,1,Assumptions!$B$5) -> 520 | G59: Office only. Unit utilities sit with the owner under the commission-only model.
A60: Mobile & telephone | B60: AED/month | C60: 150 | D60: 260 | E60: 420 | F60: =INDEX(C60:E60,1,Assumptions!$B$5) -> 260 | G60: Includes the dedicated 24/7 guest line.
A61: Transport, fuel, Salik & parking | B61: AED/month | C61: 500 | D61: 1100 | E61: 2200 | F61: =INDEX(C61:E61,1,Assumptions!$B$5) -> 1100 | G61: Check-ins, inspections and owner meetings across Dubai. Rises directly with unit count — the most commonly underestimated line in this business.
A62: Office consumables, printing & courier | B62: AED/month | C62: 100 | D62: 200 | E62: 380 | F62: =INDEX(C62:E62,1,Assumptions!$B$5) -> 200 | G62: Contracts, DET paperwork, key courier.
A63: Bank charges & account maintenance | B63: AED/month | C63: 100 | D63: 175 | E63: 320 | F63: =INDEX(C63:E63,1,Assumptions!$B$5) -> 175 | G63: Multi-currency corporate current account per the Business Profile.
A64: Payment gateway / OTA payout fees | B64: % of gross collections | C64: 0.018 | D64: 0.026 | E64: 0.032 | F64: =INDEX(C64:E64,1,Assumptions!$B$5) -> 0.026 | G64: Applied to gross booking revenue passing through Orizuru's account. Excluded if the OTA pays the owner directly — set to 0 in that case.
A65: 9. PROFESSIONAL, COMPLIANCE & INSURANCE
A66: Bookkeeping & management accounts | B66: AED/month | C66: 500 | D66: 900 | E66: 1600 | F66: =INDEX(C66:E66,1,Assumptions!$B$5) -> 900 | G66: Outsourced. Cheaper and more reliable than an in-house hire at this scale.
A67: VAT return preparation & filing | B67: AED/quarter | C67: 400 | D67: 700 | E67: 1200 | F67: =INDEX(C67:E67,1,Assumptions!$B$5) -> 700 | G67: Quarterly filing. Charged in Months 3, 6, 9 and 12.
A68: Corporate Tax compliance & filing | B68: AED/year | C68: 2500 | D68: 4000 | E68: 6500 | F68: =INDEX(C68:E68,1,Assumptions!$B$5) -> 4000 | G68: UAE Corporate Tax at 9% above AED 375,000 taxable profit. Compliance cost only — tax itself is not OPEX.
A69: External audit | B69: AED/year | C69: 3500 | D69: 6000 | E69: 10000 | F69: =INDEX(C69:E69,1,Assumptions!$B$5) -> 6000 | G69: Accrued monthly. Banks and owners increasingly require audited accounts.
A70: PRO / government liaison services | B70: AED/year | C70: 1500 | D70: 2800 | E70: 4500 | F70: =INDEX(C70:E70,1,Assumptions!$B$5) -> 2800 | G70: Visa renewals, licence amendments, DET filings.
A71: Trade licence & DET operator permit renewal | B71: AED/year | C71: 14000 | D71: 19000 | E71: 26000 | F71: =INDEX(C71:E71,1,Assumptions!$B$5) -> 19000 | G71: Accrued monthly so the renewal does not blow a hole in one month's cash. Combines DED licence and DET operator permit renewal.
A72: Public liability & professional indemnity insurance | B72: AED/year | C72: 3000 | D72: 5500 | E72: 9500 | F72: =INDEX(C72:E72,1,Assumptions!$B$5) -> 5500 | G72: Essential — Orizuru holds keys to and controls access to other people's property.
A73: Legal, contract templates & disputes | B73: AED/year | C73: 1500 | D73: 3000 | E73: 6000 | F73: =INDEX(C73:E73,1,Assumptions!$B$5) -> 3000 | G73: Management agreements, owner disputes, guest damage claims.
A74: 10. CONTINGENCY
A75: Contingency | B75: % of total OPEX | C75: 0.03 | D75: 0.05 | E75: 0.08 | F75: =INDEX(C75:E75,1,Assumptions!$B$5) -> 0.05 | G75: First-year UAE service company. 5% is the prudent base.

Sheet CAPEX Summary
A1: CAPEX SUMMARY BY CATEGORY
A2: All figures AED. Base case is the presentation figure; Low / High frame the range.
A4: Category | B4: Low | C4: Base | D4: High | E4: % of Base total | F4: Comment
A5: A. COMPANY FORMATION, LICENSING & REGULATORY | B5: ='CAPEX Detail'!G45 -> 29437 | C5: ='CAPEX Detail'!H45 -> 45337 | D5: ='CAPEX Detail'!I45 -> 62837 | E5: =IF($C$12=0,0,C5/$C$12) -> 0.37419609 | F5: Largely fixed and largely unavoidable. Most of it is already incurred as at 03/07/2026.
A6: B. TECHNOLOGY, PLATFORM & DIGITAL SETUP | B6: ='CAPEX Detail'!G46 -> 10287 | C6: ='CAPEX Detail'!H46 -> 19787 | D6: ='CAPEX Detail'!I46 -> 37887 | E6: =IF($C$12=0,0,C6/$C$12) -> 0.16331513 | F6: The direct booking engine is the highest-return line in the whole CAPEX — it removes OTA commission on repeat guests.
A7: C. BRAND & MARKETING SETUP | B7: ='CAPEX Detail'!G47 -> 6200 | C7: ='CAPEX Detail'!H47 -> 11900 | D7: ='CAPEX Detail'!I47 -> 23800 | E7: =IF($C$12=0,0,C7/$C$12) -> 0.09821853 | F7: Directly enables both marketing options. The owner pitch deck is what the acquisition team actually sells with.
A8: D. OFFICE EQUIPMENT & FURNITURE (DUBAI) | B8: ='CAPEX Detail'!G48 -> 9900 | C8: ='CAPEX Detail'!H48 -> 15000 | D8: ='CAPEX Detail'!I48 -> 24300 | E8: =IF($C$12=0,0,C8/$C$12) -> 0.12380487 | F8: Scale-insensitive. Same cost at 1 unit or 80.
A9: E. DEPOSITS & PREPAYMENTS | B9: ='CAPEX Detail'!G49 -> 5000 | C9: ='CAPEX Detail'!H49 -> 9800 | D9: ='CAPEX Detail'!I49 -> 17500 | E9: =IF($C$12=0,0,C9/$C$12) -> 0.080885849 | F9: Mostly refundable. Cash timing rather than true cost.
A10: Unit setup — 1 unit | B10: ='CAPEX Detail'!G51 -> 6105 | C10: ='CAPEX Detail'!H51 -> 9152 | D10: ='CAPEX Detail'!I51 -> 13640 | E10: =IF($C$12=0,0,C10/$C$12) -> 0.075537478 | F10: Per management: one unit only. Multiply on the 'Unit Setup' tab for portfolio scale.
A11: Contingency | B11: ='CAPEX Detail'!G52 -> 6082.4 | C11: ='CAPEX Detail'!H52 -> 10182.4 | D11: ='CAPEX Detail'!I52 -> 16632.4 | E11: =IF($C$12=0,0,C11/$C$12) -> 0.084042047 | F11: 10% of company-setup subtotal.
A12: TOTAL CAPEX | B12: =SUM(B5:B11) -> 73011.4 | C12: =SUM(C5:C11) -> 121158.4 | D12: =SUM(D5:D11) -> 196596.4 | E12: =IF($C$12=0,0,SUM(E5:E11)) -> 1
A15: READ-ACROSS
A16: • Shareholder capital is AED 200,000 as confirmed. The Business Profile states AED 2,000,000 — reconcile the two before submission. This CAPEX is not sized to either figure; it is built bottom-up from what the business needs. At AED 200,000, CAPEX alone consumes a significant share of the capital — see 'Funding Summary'.
A17: • Because Orizuru operates commission-only, CAPEX is genuinely light: there is no furniture, no unit deposits and no master-lease prepayment. The heavy spend in this business is OPEX, not CAPEX.
A18: • The single largest scaling risk is NOT in this workbook: it is the per-unit setup cost multiplied out. At the Business Profile's 70–80 unit target the unit-setup line alone becomes material — see the scaling table on the 'Unit Setup' tab.
A19: • Refundable items (office deposit, DEWA deposit, labour guarantee) are inside the total. Strip them out if presenting a 'true sunk cost' figure.

Sheet CAPEX Detail
A1: CAPEX DETAIL — ONE-OFF SETUP EXPENDITURE
A2: Company formation, licensing, technology, brand and equipment. Unit setup is on the 'Unit Setup (1 Unit)' tab.
A4: Ref | B4: Line item | C4: Qty | D4: Unit cost — Low | E4: Unit cost — Base | F4: Unit cost — High | G4: Total — Low | H4: Total — Base | I4: Total — High | J4: Timing / status | K4: Basis / note
A5: A. COMPANY FORMATION, LICENSING & REGULATORY
A6: A1 | B6: DED trade licence — initial issue (Vacation Homes Rental) | C6: 1 | D6: 13500 | E6: 17500 | F6: 22000 | G6: =$C6*D6 -> 13500 | H6: =$C6*E6 -> 17500 | I6: =$C6*F6 -> 22000 | J6: Incurred — 03/07/2026 | K6: Mainland LLC commercial licence. Licence No. 1634278 per the Business Profile.
A7: A2 | B7: Trade name reservation & initial approval | C7: 1 | D7: 900 | E7: 1200 | F7: 1600 | G7: =$C7*D7 -> 900 | H7: =$C7*E7 -> 1200 | I7: =$C7*F7 -> 1600 | J7: Incurred — 03/07/2026 | K7: DED fixed fees.
A8: A3 | B8: MOA drafting & notarisation | C8: 1 | D8: 1800 | E8: 2500 | F8: 3500 | G8: =$C8*D8 -> 1800 | H8: =$C8*E8 -> 2500 | I8: =$C8*F8 -> 3500 | J8: Incurred — 03/07/2026 | K8: Three-shareholder structure per the Business Profile (Podocarpus 70% / Atayev 16% / Mamiyev 14%).
A9: A4 | B9: Ejari / tenancy registration for the licensed address | C9: 1 | D9: 1500 | E9: 2200 | F9: 3200 | G9: =$C9*D9 -> 1500 | H9: =$C9*E9 -> 2200 | I9: =$C9*F9 -> 3200 | J9: Incurred — 03/07/2026 | K9: Fronds Building – Office 02, Goze Industrial Third. Required to hold the licence.
A10: A5 | B10: Immigration establishment card | C10: 1 | D10: 1000 | E10: 1500 | F10: 2200 | G10: =$C10*D10 -> 1000 | H10: =$C10*E10 -> 1500 | I10: =$C10*F10 -> 2200 | J10: Month 1 | K10: Required before any employment visa can be issued.
A11: A6 | B11: MOHRE labour file / e-Channel registration | C11: 1 | D11: 1600 | E11: 2300 | F11: 3200 | G11: =$C11*D11 -> 1600 | H11: =$C11*E11 -> 2300 | I11: =$C11*F11 -> 3200 | J11: Month 1 | K11: Needed to sponsor the operations & service staff member.
A12: A7 | B12: DET (ex-DTCM) holiday-home OPERATOR permit — company level | C12: 1 | D12: 4500 | E12: 7500 | F12: 12000 | G12: =$C12*D12 -> 4500 | H12: =$C12*E12 -> 7500 | I12: =$C12*F12 -> 12000 | J12: Month 1 | K12: Distinct from the per-unit permit. Without it the company cannot legally list short-term rentals.
A13: A8 | B13: Corporate bank account opening & KYC pack | C13: 1 | D13: 0 | E13: 500 | F13: 1500 | G13: =$C13*D13 -> 0 | H13: =$C13*E13 -> 500 | I13: =$C13*F13 -> 1500 | J13: Month 1 | K13: Corporate current account, multi-currency AED/USD/EUR per the Business Profile.
A14: A9 | B14: VAT registration & Corporate Tax registration | C14: 1 | D14: 0 | E14: 1000 | F14: 2500 | G14: =$C14*D14 -> 0 | H14: =$C14*E14 -> 1000 | I14: =$C14*F14 -> 2500 | J14: Incurred | K14: TRN 105507385000001 already issued per the Business Profile. Cost shown for completeness.
A15: A10 | B15: Company stamp | C15: 1 | D15: 137 | E15: 137 | F15: 137 | G15: =$C15*D15 -> 137 | H15: =$C15*E15 -> 137 | I15: =$C15*F15 -> 137 | J15: Incurred | K15: Actual figure supplied by management — AED 137.
A16: A11 | B16: Employment visa — operations & service staff (1 person) | C16: 1 | D16: 4500 | E16: 6000 | F16: 8000 | G16: =$C16*D16 -> 4500 | H16: =$C16*E16 -> 6000 | I16: =$C16*F16 -> 8000 | J16: Month 1 | K16: Entry permit, status change, medical, Emirates ID, 2-year residence visa.
A17: A12 | B17: Refundable labour guarantee / bank guarantee (1 employee) | C17: 1 | D17: 0 | E17: 3000 | F17: 3000 | G17: =$C17*D17 -> 0 | H17: =$C17*E17 -> 3000 | I17: =$C17*F17 -> 3000 | J17: Month 1 | K17: MOHRE requirement. Refundable, but cash out on day one.
A18: B. TECHNOLOGY, PLATFORM & DIGITAL SETUP
A19: B1 | B19: Domain name registration — 3 years | C19: 1 | D19: 387 | E19: 387 | F19: 387 | G19: =$C19*D19 -> 387 | H19: =$C19*E19 -> 387 | I19: =$C19*F19 -> 387 | J19: Incurred | K19: Actual figure supplied by management — AED 387 for 3 years.
A20: B2 | B20: Website build + direct booking engine | C20: 1 | D20: 7000 | E20: 12000 | F20: 22000 | G20: =$C20*D20 -> 7000 | H20: =$C20*E20 -> 12000 | I20: =$C20*F20 -> 22000 | J20: Month 1–2 | K20: The Business Profile commits to a direct booking portal. Direct bookings avoid the 15–18% OTA commission, so this pays back fastest of any line here.
A21: B3 | B21: PMS / channel manager onboarding & setup fee (Hostaway, Guesty or equivalent) | C21: 1 | D21: 1800 | E21: 3000 | F21: 5500 | G21: =$C21*D21 -> 1800 | H21: =$C21*E21 -> 3000 | I21: =$C21*F21 -> 5500 | J21: Month 1 | K21: One-off implementation. The recurring per-unit licence sits in OPEX.
A22: B4 | B22: Channel account setup & verification (Airbnb, Booking.com, direct) | C22: 1 | D22: 0 | E22: 800 | F22: 1800 | G22: =$C22*D22 -> 0 | H22: =$C22*E22 -> 800 | I22: =$C22*F22 -> 1800 | J22: Month 1 | K22: Account verification, payout setup, listing template build.
A23: B5 | B23: Business email, Google Workspace & cloud drive setup | C23: 1 | D23: 300 | E23: 600 | F23: 1200 | G23: =$C23*D23 -> 300 | H23: =$C23*E23 -> 600 | I23: =$C23*F23 -> 1200 | J23: Month 1 | K23: One-off configuration. Seat licences are OPEX.
A24: B6 | B24: Accounting system setup & chart of accounts (Zoho Books / Xero) | C24: 1 | D24: 800 | E24: 1500 | F24: 3000 | G24: =$C24*D24 -> 800 | H24: =$C24*E24 -> 1500 | I24: =$C24*F24 -> 3000 | J24: Month 1 | K24: VAT-compliant chart of accounts. Doing this properly now avoids a costly first-audit clean-up.
A25: B7 | B25: AI workspace setup — prompt library, SOP automation, guest-messaging templates | C25: 1 | D25: 0 | E25: 1500 | F25: 4000 | G25: =$C25*D25 -> 0 | H25: =$C25*E25 -> 1500 | I25: =$C25*F25 -> 4000 | J25: Month 1–2 | K25: One-off build of the AI operating layer. The recurring subscription cost sits in OPEX per management item 5.
A26: C. BRAND & MARKETING SETUP
A27: C1 | B27: Brand identity — logo, typography, Japanese-inspired visual system | C27: 1 | D27: 2500 | E27: 4500 | F27: 9000 | G27: =$C27*D27 -> 2500 | H27: =$C27*E27 -> 4500 | I27: =$C27*F27 -> 9000 | J27: Month 1 | K27: Supports the Ma / Shibui / Bushido / Wabi-Sabi brand philosophy in the Business Profile.
A28: C2 | B28: Brand photography & short-form video (company level, not per unit) | C28: 1 | D28: 2000 | E28: 3500 | F28: 7000 | G28: =$C28*D28 -> 2000 | H28: =$C28*E28 -> 3500 | I28: =$C28*F28 -> 7000 | J28: Month 1–2 | K28: Used across the website, OTA profile and owner pitch deck.
A29: C3 | B29: Owner acquisition pitch deck & management-contract pack | C29: 1 | D29: 800 | E29: 1800 | F29: 3500 | G29: =$C29*D29 -> 800 | H29: =$C29*E29 -> 1800 | I29: =$C29*F29 -> 3500 | J29: Month 1 | K29: The core sales asset for the marketing team in both Option 1 and Option 2.
A30: C4 | B30: Printed collateral, business cards, owner welcome pack | C30: 1 | D30: 400 | E30: 900 | F30: 1800 | G30: =$C30*D30 -> 400 | H30: =$C30*E30 -> 900 | I30: =$C30*F30 -> 1800 | J30: Month 1
A31: C5 | B31: Social media profile setup & launch content batch | C31: 1 | D31: 500 | E31: 1200 | F31: 2500 | G31: =$C31*D31 -> 500 | H31: =$C31*E31 -> 1200 | I31: =$C31*F31 -> 2500 | J31: Month 1
A32: D. OFFICE EQUIPMENT & FURNITURE (DUBAI)
A33: D1 | B33: Laptop — operations | C33: 2 | D33: 2800 | E33: 3800 | F33: 5500 | G33: =$C33*D33 -> 5600 | H33: =$C33*E33 -> 7600 | I33: =$C33*F33 -> 11000 | J33: Month 1 | K33: One for the operations & service staff member, one for management.
A34: D2 | B34: Mobile handset — dedicated 24/7 guest support line | C34: 1 | D34: 1200 | E34: 1900 | F34: 3200 | G34: =$C34*D34 -> 1200 | H34: =$C34*E34 -> 1900 | I34: =$C34*F34 -> 3200 | J34: Month 1 | K34: The Business Profile promises 24/7 guest support. It needs its own line and device.
A35: D3 | B35: Printer / scanner (contracts, DET paperwork) | C35: 1 | D35: 500 | E35: 850 | F35: 1500 | G35: =$C35*D35 -> 500 | H35: =$C35*E35 -> 850 | I35: =$C35*F35 -> 1500 | J35: Month 1
A36: D4 | B36: Office desk, chairs & storage | C36: 1 | D36: 1800 | E36: 3200 | F36: 6000 | G36: =$C36*D36 -> 1800 | H36: =$C36*E36 -> 3200 | I36: =$C36*F36 -> 6000 | J36: Month 1
A37: D5 | B37: Key-safe cabinet & spare-key management system | C37: 1 | D37: 500 | E37: 900 | F37: 1600 | G37: =$C37*D37 -> 500 | H37: =$C37*E37 -> 900 | I37: =$C37*F37 -> 1600 | J37: Month 1 | K37: Physical key control across a multi-unit portfolio. An audit point for owners.
A38: D6 | B38: Router, networking & basic office IT | C38: 1 | D38: 300 | E38: 550 | F38: 1000 | G38: =$C38*D38 -> 300 | H38: =$C38*E38 -> 550 | I38: =$C38*F38 -> 1000 | J38: Month 1
A39: E. DEPOSITS & PREPAYMENTS
A40: E1 | B40: Office rent security deposit (refundable) | C40: 1 | D40: 2500 | E40: 5000 | F40: 9000 | G40: =$C40*D40 -> 2500 | H40: =$C40*E40 -> 5000 | I40: =$C40*F40 -> 9000 | J40: Month 1 | K40: Refundable at lease end. Cash out on day one.
A41: E2 | B41: DEWA office connection deposit (refundable) | C41: 1 | D41: 1000 | E41: 2000 | F41: 3500 | G41: =$C41*D41 -> 1000 | H41: =$C41*E41 -> 2000 | I41: =$C41*F41 -> 3500 | J41: Month 1 | K41: Refundable.
A42: E3 | B42: Public liability & professional indemnity — first-year premium prepayment | C42: 1 | D42: 1500 | E42: 2800 | F42: 5000 | G42: =$C42*D42 -> 1500 | H42: =$C42*E42 -> 2800 | I42: =$C42*F42 -> 5000 | J42: Month 1 | K42: Insurers commonly require the first year up front. The ongoing accrual also appears in OPEX — do not double-count when consolidating; treat this as the timing of the cash, not an extra cost.
A44: TOTALS
B45: A. COMPANY FORMATION, LICENSING & REGULATORY | G45: =SUM(G6:G17) -> 29437 | H45: =SUM(H6:H17) -> 45337 | I45: =SUM(I6:I17) -> 62837
B46: B. TECHNOLOGY, PLATFORM & DIGITAL SETUP | G46: =SUM(G19:G25) -> 10287 | H46: =SUM(H19:H25) -> 19787 | I46: =SUM(I19:I25) -> 37887
B47: C. BRAND & MARKETING SETUP | G47: =SUM(G27:G31) -> 6200 | H47: =SUM(H27:H31) -> 11900 | I47: =SUM(I27:I31) -> 23800
B48: D. OFFICE EQUIPMENT & FURNITURE (DUBAI) | G48: =SUM(G33:G38) -> 9900 | H48: =SUM(H33:H38) -> 15000 | I48: =SUM(I33:I38) -> 24300
B49: E. DEPOSITS & PREPAYMENTS | G49: =SUM(G40:G42) -> 5000 | H49: =SUM(H40:H42) -> 9800 | I49: =SUM(I40:I42) -> 17500
B50: SUBTOTAL — company setup (excl. unit setup) | G50: =G45+G46+G47+G48+G49 -> 60824 | H50: =H45+H46+H47+H48+H49 -> 101824 | I50: =I45+I46+I47+I48+I49 -> 166324
B51: Unit setup CAPEX — 1 unit | G51: ='Unit Setup (1 Unit)'!D17 -> 6105 | H51: ='Unit Setup (1 Unit)'!E17 -> 9152 | I51: ='Unit Setup (1 Unit)'!F17 -> 13640 | K51: Links to 'Unit Setup (1 Unit)'. Per management, sized for one unit only.
B52: Contingency on company setup | C52: 0.1 | G52: =G50*$C$52 -> 6082.4 | H52: =H50*$C$52 -> 10182.4 | I52: =I50*$C$52 -> 16632.4 | K52: Unit-setup contingency is already applied on its own tab — not double-counted here.
B53: TOTAL CAPEX REQUIRED | G53: =G50+G51+G52 -> 73011.4 | H53: =H50+H51+H52 -> 121158.4 | I53: =I50+I51+I52 -> 196596.4
B55: MEMO — not CAPEX
B56: Bank minimum / average balance requirement (blocked, not a cost) | G56: 25000 | H56: 50000 | I56: 150000 | K56: UAE corporate accounts typically require an average balance of AED 25k–150k depending on the bank. It is a blocked asset, not expenditure — excluded from the CAPEX total above.
B57: Refundable deposits included above (E1, E2, A12) | G57: =G17+G40+G41 -> 3500 | H57: =H17+H40+H41 -> 10000 | I57: =I17+I40+I41 -> 15500 | K57: Cash out on day one but recoverable. Useful for the bank when distinguishing sunk cost from working capital.

Sheet Unit Setup (1 Unit)
A1: UNIT SETUP CAPEX — COST TO BRING ONE UNIT LIVE
A2: Commission-only model: the owner supplies the furnished apartment. Orizuru funds only the operating layer.
A4: Ref | B4: Line item | C4: Qty | D4: Unit cost — Low | E4: Unit cost — Base | F4: Unit cost — High | G4: Total — Base | H4: Basis / note
A5: U1 | B5: DET holiday-home permit — first issue (per unit, per year) | C5: 1 | D5: 1200 | E5: 1520 | F5: 1800 | G5: =C5*E5 -> 1520 | H5: Dubai Dept. of Economy & Tourism per-unit permit. Usually re-charged to the owner — confirm in the management contract.
A6: U2 | B6: Smart lock / keyless entry device + install | C6: 1 | D6: 850 | E6: 1200 | F6: 1700 | G6: =C6*E6 -> 1200 | H6: Essential for self check-in. Removes the cost of a physical key handover per booking.
A7: U3 | B7: Professional listing photography (unit) | C7: 1 | D7: 500 | E7: 800 | F7: 1400 | G7: =C7*E7 -> 800 | H7: Single biggest driver of conversion on Airbnb / Booking.com. Do not economise here.
A8: U4 | B8: Linen & towel par stock — 3 sets | C8: 1 | D8: 1100 | E8: 1800 | F8: 2600 | G8: =C8*E8 -> 1800 | H8: 3 sets allows one in use, one in laundry, one on the shelf. Required for same-day turnovers.
A9: U5 | B9: Welcome & amenity kit (branded, Japanese-hospitality standard) | C9: 1 | D9: 300 | E9: 450 | F9: 700 | G9: =C9*E9 -> 450 | H9: Brand differentiator per the Ma / Shibui positioning in the Business Profile.
A10: U6 | B10: Safety kit — smoke detector, fire extinguisher, first-aid box | C10: 1 | D10: 380 | E10: 550 | F10: 800 | G10: =C10*E10 -> 550 | H10: DET holiday-home inspection requirement.
A11: U7 | B11: Small appliances & inventory top-up (kettle, iron, hairdryer, crockery gaps) | C11: 1 | D11: 500 | E11: 900 | F11: 1600 | G11: =C11*E11 -> 900 | H11: Covers the gap between what the owner supplies and DET / guest expectation.
A12: U8 | B12: Initial deep clean & staging before first listing | C12: 1 | D12: 400 | E12: 600 | F12: 950 | G12: =C12*E12 -> 600 | H12: One-off. Routine turnover cleaning sits in OPEX.
A13: U9 | B13: Inventory & condition report, listing build, channel sync | C13: 1 | D13: 200 | E13: 300 | F13: 500 | G13: =C13*E13 -> 300 | H13: Protects against damage disputes and is the baseline for owner reporting.
A14: U10 | B14: Guest welcome book, house rules, signage (printed) | C14: 1 | D14: 120 | E14: 200 | F14: 350 | G14: =C14*E14 -> 200 | H14: Reduces avoidable guest-support contacts.
B15: Subtotal — per unit | D15: =SUMPRODUCT($C$5:$C$14,D5:D14) -> 5550 | E15: =SUMPRODUCT($C$5:$C$14,E5:E14) -> 8320 | F15: =SUMPRODUCT($C$5:$C$14,F5:F14) -> 12400 | G15: =SUM(G5:G14) -> 8320
B16: Contingency | C16: 0.1 | D16: =D15*$C$16 -> 555 | E16: =E15*$C$16 -> 832 | F16: =F15*$C$16 -> 1240 | G16: =G15*$C$16 -> 832 | H16: Applied to the per-unit subtotal. Covers price movement on permits and hardware.
B17: TOTAL CAPEX PER UNIT | D17: =D15+D16 -> 6105 | E17: =E15+E16 -> 9152 | F17: =F15+F16 -> 13640 | G17: =G15+G16 -> 9152
A20: PORTFOLIO SCALING REFERENCE — FOR INFORMATION ONLY, NOT INCLUDED IN THE CAPEX TOTAL
A21: Per management, the CAPEX total is built for ONE unit. This table shows what the same unit-setup cost becomes at portfolio scale, against the Business Profile's 70–80 unit Year-1 target.
A23: Units | B23: Total — Low | C23: Total — Base | D23: Total — High
A24: 1 | B24: =$A24*D$17 -> 6105 | C24: =$A24*E$17 -> 9152 | D24: =$A24*F$17 -> 13640
A25: 5 | B25: =$A25*D$17 -> 30525 | C25: =$A25*E$17 -> 45760 | D25: =$A25*F$17 -> 68200
A26: 10 | B26: =$A26*D$17 -> 61050 | C26: =$A26*E$17 -> 91520 | D26: =$A26*F$17 -> 136400
A27: 25 | B27: =$A27*D$17 -> 152625 | C27: =$A27*E$17 -> 228800 | D27: =$A27*F$17 -> 341000
A28: 50 | B28: =$A28*D$17 -> 305250 | C28: =$A28*E$17 -> 457600 | D28: =$A28*F$17 -> 682000
A29: 80 | B29: =$A29*D$17 -> 488400 | C29: =$A29*E$17 -> 732160 | D29: =$A29*F$17 -> 1091200

Sheet OPEX Summary
A1: OPEX SUMMARY — YEAR 1
A2: All figures AED. Reads live from 'OPEX Monthly'. Change the scenario on the Assumptions tab to re-cut it.
A4: Category | B4: FY1 total | C4: Monthly average | D4: % of total OPEX | F4: Comment
A5: A. STAFF COSTS | B5: ='OPEX Monthly'!O22 -> 64242 | C5: =B5/12 -> 5353.5 | D5: =IF($B$14=0,0,B5/$B$14) -> 0.090007816 | F5: Headcount now scales with the portfolio (see the staffing ratio on Assumptions). Still understated: directors work unpaid.
A6: B. Marketing — Option 1 (fully online) | B6: ='OPEX Monthly'!O29 -> 7760 | C6: =B6/12 -> 646.66667 | D6: =IF($B$14=0,0,B6/$B$14) -> 0.010872337 | F6: Runs M1–M2 only unless adopted from M3 on the Assumptions tab.
A7: C. Marketing — Option 2 (remote office) | B7: ='OPEX Monthly'!O38 -> 57300 | C7: =B7/12 -> 4775 | D7: =IF($B$14=0,0,B7/$B$14) -> 0.080281558 | F7: Runs M1–M2 only unless adopted from M3 on the Assumptions tab.
A8: D. Unit-acquisition commission (2%) | B8: ='OPEX Monthly'!O42 -> 75103.2 | C8: =B8/12 -> 6258.6 | D8: =IF($B$14=0,0,B8/$B$14) -> 0.10522516 | F8: Grows every month as the portfolio grows — this is the line that scales fastest of anything here.
A9: E. TECHNOLOGY, PLATFORM & AI | B9: ='OPEX Monthly'!O53 -> 70331.13 | C9: =B9/12 -> 5860.9275 | D9: =IF($B$14=0,0,B9/$B$14) -> 0.09853914 | F9: Part fixed (AI, Workspace, website), part per-unit (PMS, pricing, locks). Includes the AI subscriptions specified by management.
A10: F. UNIT OPERATIONS | B10: ='OPEX Monthly'!O61 -> 196420 | C10: =B10/12 -> 16368.333 | D10: =IF($B$14=0,0,B10/$B$14) -> 0.27519902 | F10: Fully variable. Much of it is re-chargeable to owners or guests — set the relevant assumptions to 0 if you recharge.
A11: G. OFFICE & ADMINISTRATION | B11: ='OPEX Monthly'!O71 -> 154694.16 | C11: =B11/12 -> 12891.18 | D11: =IF($B$14=0,0,B11/$B$14) -> 0.21673801 | F11: Mostly fixed. Transport is the one line that climbs with unit count.
A12: H. PROFESSIONAL, COMPLIANCE & INSURANCE | B12: ='OPEX Monthly'!O82 -> 53900 | C12: =B12/12 -> 4491.6667 | D12: =IF($B$14=0,0,B12/$B$14) -> 0.075517906 | F12: Annual costs accrued monthly so no single month takes the hit. Non-negotiable for a licensed UAE entity.
A13: Contingency | B13: ='OPEX Monthly'!O86 -> 33987.524 | C13: =B13/12 -> 2832.2937 | D13: =IF($B$14=0,0,B13/$B$14) -> 0.047619048 | F13: Set on the Assumptions tab.
A14: TOTAL OPEX — YEAR 1 | B14: =SUM(B5:B13) -> 713738.01 | C14: =B14/12 -> 59478.168 | D14: =IF($B$14=0,0,SUM(D5:D13)) -> 1
A16: KEY METRICS — YEAR 1
A17: Units signed by end of Year 1 | B17: ='OPEX Monthly'!N8 -> 80 | F17: Against the Business Profile's 70–80 unit Year-1 target.
A18: Gross booking revenue (portfolio, guest spend) | B18: ='OPEX Monthly'!O11 -> 3755160 | F18: This is what guests pay across the portfolio — NOT Orizuru's revenue.
A19: Orizuru revenue (management fees) | B19: ='OPEX Monthly'!O12 -> 751032 | F19: Orizuru's actual top line under the commission-only model.
A20: Total OPEX | B20: =B14 -> 713738.01
A21: Operating surplus / (deficit) | B21: ='OPEX Monthly'!O92 -> 37293.986 | F21: Before corporate tax and before any director remuneration.
A22: Peak cash requirement (worst cumulative month) | B22: =MIN('OPEX Monthly'!C93:N93) -> -76726.005 | F22: The most negative the cumulative operating cash position ever gets. THIS is the working capital number to fund — not the annual OPEX figure.
A23: OPEX as % of Orizuru revenue | B23: =IF(B19=0,0,B20/B19) -> 0.95034301 | F23: Total OPEX divided by Orizuru's management fee revenue. Above 100% means Year 1 runs at a loss — normal while the portfolio ramps.
A24: Exit-run-rate monthly OPEX (Month 12) | B24: ='OPEX Monthly'!N87 -> 113117.82 | F24: The steady-state monthly cost you carry into Year 2.
A25: OPEX per live unit at Month 12 | B25: ='OPEX Monthly'!N95 -> 1593.2087 | F25: Efficiency measure. Should fall steadily as the portfolio grows.
A27: WHAT I ADDED THAT WAS NOT IN YOUR BRIEF — AND WHY
A28: • Staff visa, medical insurance, Emirates ID and end-of-service gratuity. AED 3,000/month is the salary, not the cost of employing someone in the UAE. The true loaded cost is roughly 45–50% higher.
A29: • Trade licence and DET operator permit renewal, accrued monthly. These arrive as a single large annual bill and sink first-year cash plans that ignored them.
A30: • Public liability and professional indemnity insurance. Orizuru holds keys to other people's property — this is not optional.
A31: • External audit and Corporate Tax compliance. UAE Corporate Tax applies above AED 375,000 of taxable profit; the compliance cost applies regardless.
A32: • Transport, fuel, Salik and parking. Check-ins and inspections across Dubai at 70–80 units. Consistently the most underestimated line in holiday-home management.
A33: • Per-unit software: PMS/channel manager, dynamic pricing, smart-lock platform. These are priced per property, so they scale with the portfolio and are easy to miss when modelling a single unit.
A34: • For Option 2: local utilities, an on-site supervisor, and a compliant offshore contracting route. A room with 4–6 people in it costs more than rent plus wages.
A35: • Contingency. First-year UAE service company with regulatory fees in motion.
A37: THREE THINGS TO LOOK AT BEFORE YOU CIRCULATE THIS
A38: • STAFFING NOW SCALES WITH THE PORTFOLIO. Headcount is driven by the 'live units per operations staff member' ratio on the Assumptions tab (35 in the Base case), with a floor of one person. The team grows through Year 1 as units come live rather than staying at one person for 80 units, which was never realistic. Tighten or loosen the ratio there — it is the single input that decides staff cost.
A39: • REVENUE RECOGNITION vs THE BUSINESS PROFILE. The profile projects AED 2.5–4.5M Year-1 turnover. Under a pure commission-only model at 70–80 units, Orizuru's own revenue is materially lower — the AED 2.5–4.5M is closer to gross booking value passing through. Agree with your accountant and the bank which figure you are presenting before submission; they are very different numbers.
A40: • THE 2% IS ONGOING, NOT ONE-OFF. As instructed, it applies to every live unit every month, forever. By Month 12 it is one of the larger single lines in the model and it never stops growing. If the intent was a one-off signing incentive, tell me and I will re-cut it — the difference over three years is very large.

Sheet OPEX Monthly
A1: OPEX — MONTH BY MONTH, YEAR 1
A2: All figures AED. Commission-only model: no unit rent, no owner utilities. Driven entirely by the Assumptions tab — change the scenario there and this whole sheet moves.
A4: Line item | B4: Basis | C4: M1 | D4: M2 | E4: M3 | F4: M4 | G4: M5 | H4: M6 | I4: M7 | J4: M8 | K4: M9 | L4: M10 | M4: M11 | N4: M12 | O4: FY1 TOTAL | P4: % of OPEX
A5: DRIVERS — edit the yellow ramp row to change the whole model
A6: Month number | C6: 1 | D6: 2 | E6: 3 | F6: 4 | G6: 5 | H6: 6 | I6: 7 | J6: 8 | K6: 9 | L6: 10 | M6: 11 | N6: 12
A7: New units signed in month | B7: Input — editable | C7: 3 | D7: 4 | E7: 5 | F7: 6 | G7: 6 | H7: 7 | I7: 7 | J7: 8 | K7: 8 | L7: 8 | M7: 9 | N7: 9 | O7: =SUM(C7:N7) -> 80
A8: Cumulative units signed | B8: Running total | C8: =C7 -> 3 | D8: =C8+D7 -> 7 | E8: =D8+E7 -> 12 | F8: =E8+F7 -> 18 | G8: =F8+G7 -> 24 | H8: =G8+H7 -> 31 | I8: =H8+I7 -> 38 | J8: =I8+J7 -> 46 | K8: =J8+K7 -> 54 | ... N8: =M8+N7 -> 80 | O8: =N8 -> 80
A9: Live revenue-generating units | B9: 1-month onboarding lag | C9: 0 | D9: =C8 -> 3 | E9: =D8 -> 7 | F9: =E8 -> 12 | G9: =F8 -> 18 | H9: =G8 -> 24 | I9: =H8 -> 31 | J9: =I8 -> 38 | K9: =J8 -> 46 | ... N9: =M8 -> 71 | O9: =N9 -> 71
A10: Operations headcount required | B10: Max(minimum, live units / ratio) | C10: =MAX(Assumptions!$F$19,ROUNDUP(C9/Assumptions!$F$20,0)) -> 1 | D10: =MAX(Assumptions!$F$19,ROUNDUP(D9/Assumptions!$F$20,0)) -> 1 | E10: =MAX(Assumptions!$F$19,ROUNDUP(E9/Assumptions!$F$20,0)) -> 1 | F10: =MAX(Assumptions!$F$19,ROUNDUP(F9/Assumptions!$F$20,0)) -> 1 | G10: =MAX(Assumptions!$F$19,ROUNDUP(G9/Assumptions!$F$20,0)) -> 1 | H10: =MAX(Assumptions!$F$19,ROUNDUP(H9/Assumptions!$F$20,0)) -> 1 | I10: =MAX(Assumptions!$F$19,ROUNDUP(I9/Assumptions!$F$20,0)) -> 1 | J10: =MAX(Assumptions!$F$19,ROUNDUP(J9/Assumptions!$F$20,0)) -> 2 | ... N10: =MAX(Assumptions!$F$19,ROUNDUP(N9/Assumptions!$F$20,0)) -> 3 | O10: =AVERAGE(C10:N10) -> 1.5
A11: Gross booking revenue (portfolio) | B11: Live units x gross rev/unit | C11: =C9*Assumptions!$F$14 -> 0 | D11: =D9*Assumptions!$F$14 -> 30780 | E11: =E9*Assumptions!$F$14 -> 71820 | F11: =F9*Assumptions!$F$14 -> 123120 | G11: =G9*Assumptions!$F$14 -> 184680 | H11: =H9*Assumptions!$F$14 -> 246240 | I11: =I9*Assumptions!$F$14 -> 318060 | J11: =J9*Assumptions!$F$14 -> 389880 | ... N11: =N9*Assumptions!$F$14 -> 728460 | O11: =SUM(C11:N11) -> 3755160
A12: Orizuru management fee revenue | B12: Gross x management fee % | C12: =C11*Assumptions!$F$15 -> 0 | D12: =D11*Assumptions!$F$15 -> 6156 | E12: =E11*Assumptions!$F$15 -> 14364 | F12: =F11*Assumptions!$F$15 -> 24624 | G12: =G11*Assumptions!$F$15 -> 36936 | H12: =H11*Assumptions!$F$15 -> 49248 | I12: =I11*Assumptions!$F$15 -> 63612 | J12: =J11*Assumptions!$F$15 -> 77976 | ... N12: =N11*Assumptions!$F$15 -> 145692 | O12: =SUM(C12:N12) -> 751032
A13: Option 1 active (1/0) | B13: Both run M1–M2 per management | C13: =IF(OR(C6<=Assumptions!$B$7,Assumptions!$B$6="Option 1",Assumptions!$B$6="Both"),1,0) -> 1 | D13: =IF(OR(D6<=Assumptions!$B$7,Assumptions!$B$6="Option 1",Assumptions!$B$6="Both"),1,0) -> 1 | E13: =IF(OR(E6<=Assumptions!$B$7,Assumptions!$B$6="Option 1",Assumptions!$B$6="Both"),1,0) -> 0 | F13: =IF(OR(F6<=Assumptions!$B$7,Assumptions!$B$6="Option 1",Assumptions!$B$6="Both"),1,0) -> 0 | G13: =IF(OR(G6<=Assumptions!$B$7,Assumptions!$B$6="Option 1",Assumptions!$B$6="Both"),1,0) -> 0 | H13: =IF(OR(H6<=Assumptions!$B$7,Assumptions!$B$6="Option 1",Assumptions!$B$6="Both"),1,0) -> 0 | I13: =IF(OR(I6<=Assumptions!$B$7,Assumptions!$B$6="Option 1",Assumptions!$B$6="Both"),1,0) -> 0 | J13: =IF(OR(J6<=Assumptions!$B$7,Assumptions!$B$6="Option 1",Assumptions!$B$6="Both"),1,0) -> 0 | ... N13: =IF(OR(N6<=Assumptions!$B$7,Assumptions!$B$6="Option 1",Assumptions!$B$6="Both"),1,0) -> 0
A14: Option 2 active (1/0) | B14: Both run M1–M2 per management | C14: =IF(OR(C6<=Assumptions!$B$7,Assumptions!$B$6="Option 2",Assumptions!$B$6="Both"),1,0) -> 1 | D14: =IF(OR(D6<=Assumptions!$B$7,Assumptions!$B$6="Option 2",Assumptions!$B$6="Both"),1,0) -> 1 | E14: =IF(OR(E6<=Assumptions!$B$7,Assumptions!$B$6="Option 2",Assumptions!$B$6="Both"),1,0) -> 1 | F14: =IF(OR(F6<=Assumptions!$B$7,Assumptions!$B$6="Option 2",Assumptions!$B$6="Both"),1,0) -> 1 | G14: =IF(OR(G6<=Assumptions!$B$7,Assumptions!$B$6="Option 2",Assumptions!$B$6="Both"),1,0) -> 1 | H14: =IF(OR(H6<=Assumptions!$B$7,Assumptions!$B$6="Option 2",Assumptions!$B$6="Both"),1,0) -> 1 | I14: =IF(OR(I6<=Assumptions!$B$7,Assumptions!$B$6="Option 2",Assumptions!$B$6="Both"),1,0) -> 1 | J14: =IF(OR(J6<=Assumptions!$B$7,Assumptions!$B$6="Option 2",Assumptions!$B$6="Both"),1,0) -> 1 | ... N14: =IF(OR(N6<=Assumptions!$B$7,Assumptions!$B$6="Option 2",Assumptions!$B$6="Both"),1,0) -> 1
A16: A. STAFF COSTS — DUBAI
A17: Directors' salary | B17: Per management — nil | C17: =Assumptions!$F$18 -> 0 | D17: =Assumptions!$F$18 -> 0 | E17: =Assumptions!$F$18 -> 0 | F17: =Assumptions!$F$18 -> 0 | G17: =Assumptions!$F$18 -> 0 | H17: =Assumptions!$F$18 -> 0 | I17: =Assumptions!$F$18 -> 0 | J17: =Assumptions!$F$18 -> 0 | ... N17: =Assumptions!$F$18 -> 0 | O17: =SUM(C17:N17) -> 0
A18: Operations & service staff | B18: Headcount x AED 3,000, scaling with units | C18: =C10*Assumptions!$F$21 -> 3000 | D18: =D10*Assumptions!$F$21 -> 3000 | E18: =E10*Assumptions!$F$21 -> 3000 | F18: =F10*Assumptions!$F$21 -> 3000 | G18: =G10*Assumptions!$F$21 -> 3000 | H18: =H10*Assumptions!$F$21 -> 3000 | I18: =I10*Assumptions!$F$21 -> 3000 | J18: =J10*Assumptions!$F$21 -> 6000 | ... N18: =N10*Assumptions!$F$21 -> 9000 | O18: =SUM(C18:N18) -> 54000
A19: Staff visa, medical insurance & EID (accrual) | B19: Per UAE employee | C19: =C10*Assumptions!$F$22 -> 380 | D19: =D10*Assumptions!$F$22 -> 380 | E19: =E10*Assumptions!$F$22 -> 380 | F19: =F10*Assumptions!$F$22 -> 380 | G19: =G10*Assumptions!$F$22 -> 380 | H19: =H10*Assumptions!$F$22 -> 380 | I19: =I10*Assumptions!$F$22 -> 380 | J19: =J10*Assumptions!$F$22 -> 760 | ... N19: =N10*Assumptions!$F$22 -> 1140 | O19: =SUM(C19:N19) -> 6840
A20: End-of-service gratuity accrual | B20: 5.8% of salary | C20: =C18*Assumptions!$F$23 -> 174 | D20: =D18*Assumptions!$F$23 -> 174 | E20: =E18*Assumptions!$F$23 -> 174 | F20: =F18*Assumptions!$F$23 -> 174 | G20: =G18*Assumptions!$F$23 -> 174 | H20: =H18*Assumptions!$F$23 -> 174 | I20: =I18*Assumptions!$F$23 -> 174 | J20: =J18*Assumptions!$F$23 -> 348 | ... N20: =N18*Assumptions!$F$23 -> 522 | O20: =SUM(C20:N20) -> 3132
A21: WPS / payroll processing | B21: Per employee | C21: =C10*Assumptions!$F$24 -> 15 | D21: =D10*Assumptions!$F$24 -> 15 | E21: =E10*Assumptions!$F$24 -> 15 | F21: =F10*Assumptions!$F$24 -> 15 | G21: =G10*Assumptions!$F$24 -> 15 | H21: =H10*Assumptions!$F$24 -> 15 | I21: =I10*Assumptions!$F$24 -> 15 | J21: =J10*Assumptions!$F$24 -> 30 | ... N21: =N10*Assumptions!$F$24 -> 45 | O21: =SUM(C21:N21) -> 270
A22: TOTAL STAFF COSTS | C22: =SUM(C17:C21) -> 3569 | D22: =SUM(D17:D21) -> 3569 | E22: =SUM(E17:E21) -> 3569 | F22: =SUM(F17:F21) -> 3569 | G22: =SUM(G17:G21) -> 3569 | H22: =SUM(H17:H21) -> 3569 | I22: =SUM(I17:I21) -> 3569 | J22: =SUM(J17:J21) -> 7138 | ... N22: =SUM(N17:N21) -> 10707 | O22: =SUM(C22:N22) -> 64242 | P22: =IF($O$87=0,0,$O22/$O$87) -> 0.090007816
A24: B. MARKETING — OPTION 1: FULLY ONLINE (switches off after M2 unless adopted)
A25: Option 1 — team cost | B25: Headcount x rate | C25: =C13*Assumptions!$F$26*Assumptions!$F$27 -> 1800 | D25: =D13*Assumptions!$F$26*Assumptions!$F$27 -> 1800 | E25: =E13*Assumptions!$F$26*Assumptions!$F$27 -> 0 | F25: =F13*Assumptions!$F$26*Assumptions!$F$27 -> 0 | G25: =G13*Assumptions!$F$26*Assumptions!$F$27 -> 0 | H25: =H13*Assumptions!$F$26*Assumptions!$F$27 -> 0 | I25: =I13*Assumptions!$F$26*Assumptions!$F$27 -> 0 | J25: =J13*Assumptions!$F$26*Assumptions!$F$27 -> 0 | ... N25: =N13*Assumptions!$F$26*Assumptions!$F$27 -> 0 | O25: =SUM(C25:N25) -> 3600
A26: Option 1 — digital ads & lead generation | C26: =C13*Assumptions!$F$28 -> 1500 | D26: =D13*Assumptions!$F$28 -> 1500 | E26: =E13*Assumptions!$F$28 -> 0 | F26: =F13*Assumptions!$F$28 -> 0 | G26: =G13*Assumptions!$F$28 -> 0 | H26: =H13*Assumptions!$F$28 -> 0 | I26: =I13*Assumptions!$F$28 -> 0 | J26: =J13*Assumptions!$F$28 -> 0 | ... N26: =N13*Assumptions!$F$28 -> 0 | O26: =SUM(C26:N26) -> 3000
A27: Option 1 — outreach tooling & CRM | C27: =C13*Assumptions!$F$29 -> 280 | D27: =D13*Assumptions!$F$29 -> 280 | E27: =E13*Assumptions!$F$29 -> 0 | F27: =F13*Assumptions!$F$29 -> 0 | G27: =G13*Assumptions!$F$29 -> 0 | H27: =H13*Assumptions!$F$29 -> 0 | I27: =I13*Assumptions!$F$29 -> 0 | J27: =J13*Assumptions!$F$29 -> 0 | ... N27: =N13*Assumptions!$F$29 -> 0 | O27: =SUM(C27:N27) -> 560
A28: Option 1 — coordination & QA | C28: =C13*Assumptions!$F$30 -> 300 | D28: =D13*Assumptions!$F$30 -> 300 | E28: =E13*Assumptions!$F$30 -> 0 | F28: =F13*Assumptions!$F$30 -> 0 | G28: =G13*Assumptions!$F$30 -> 0 | H28: =H13*Assumptions!$F$30 -> 0 | I28: =I13*Assumptions!$F$30 -> 0 | J28: =J13*Assumptions!$F$30 -> 0 | ... N28: =N13*Assumptions!$F$30 -> 0 | O28: =SUM(C28:N28) -> 600
A29: TOTAL — MARKETING OPTION 1 | C29: =SUM(C25:C28) -> 3880 | D29: =SUM(D25:D28) -> 3880 | E29: =SUM(E25:E28) -> 0 | F29: =SUM(F25:F28) -> 0 | G29: =SUM(G25:G28) -> 0 | H29: =SUM(H25:H28) -> 0 | I29: =SUM(I25:I28) -> 0 | J29: =SUM(J25:J28) -> 0 | ... N29: =SUM(N25:N28) -> 0 | O29: =SUM(C29:N29) -> 7760 | P29: =IF($O$87=0,0,$O29/$O$87) -> 0.010872337
A31: C. MARKETING — OPTION 2: REMOTE OFFICE OUTSIDE UAE (switches off after M2 unless adopted)
A32: Option 2 — team cost | B32: Headcount x rate | C32: =C14*Assumptions!$F$32*Assumptions!$F$33 -> 1200 | D32: =D14*Assumptions!$F$32*Assumptions!$F$33 -> 1200 | E32: =E14*Assumptions!$F$32*Assumptions!$F$33 -> 1200 | F32: =F14*Assumptions!$F$32*Assumptions!$F$33 -> 1200 | G32: =G14*Assumptions!$F$32*Assumptions!$F$33 -> 1200 | H32: =H14*Assumptions!$F$32*Assumptions!$F$33 -> 1200 | I32: =I14*Assumptions!$F$32*Assumptions!$F$33 -> 1200 | J32: =J14*Assumptions!$F$32*Assumptions!$F$33 -> 1200 | ... N32: =N14*Assumptions!$F$32*Assumptions!$F$33 -> 1200 | O32: =SUM(C32:N32) -> 14400
A33: Option 2 — coworking area rent | B33: Per management | C33: =C14*Assumptions!$F$34 -> 1425 | D33: =D14*Assumptions!$F$34 -> 1425 | E33: =E14*Assumptions!$F$34 -> 1425 | F33: =F14*Assumptions!$F$34 -> 1425 | G33: =G14*Assumptions!$F$34 -> 1425 | H33: =H14*Assumptions!$F$34 -> 1425 | I33: =I14*Assumptions!$F$34 -> 1425 | J33: =J14*Assumptions!$F$34 -> 1425 | ... N33: =N14*Assumptions!$F$34 -> 1425 | O33: =SUM(C33:N33) -> 17100
A34: Option 2 — local internet, utilities & equipment | B34: Not in original brief | C34: =C14*Assumptions!$F$35 -> 350 | D34: =D14*Assumptions!$F$35 -> 350 | E34: =E14*Assumptions!$F$35 -> 350 | F34: =F14*Assumptions!$F$35 -> 350 | G34: =G14*Assumptions!$F$35 -> 350 | H34: =H14*Assumptions!$F$35 -> 350 | I34: =I14*Assumptions!$F$35 -> 350 | J34: =J14*Assumptions!$F$35 -> 350 | ... N34: =N14*Assumptions!$F$35 -> 350 | O34: =SUM(C34:N34) -> 4200
A35: Option 2 — on-site supervisor / team lead | B35: Not in original brief | C35: =C14*Assumptions!$F$36 -> 500 | D35: =D14*Assumptions!$F$36 -> 500 | E35: =E14*Assumptions!$F$36 -> 500 | F35: =F14*Assumptions!$F$36 -> 500 | G35: =G14*Assumptions!$F$36 -> 500 | H35: =H14*Assumptions!$F$36 -> 500 | I35: =I14*Assumptions!$F$36 -> 500 | J35: =J14*Assumptions!$F$36 -> 500 | ... N35: =N14*Assumptions!$F$36 -> 500 | O35: =SUM(C35:N35) -> 6000
A36: Option 2 — digital ads & lead generation | C36: =C14*Assumptions!$F$37 -> 900 | D36: =D14*Assumptions!$F$37 -> 900 | E36: =E14*Assumptions!$F$37 -> 900 | F36: =F14*Assumptions!$F$37 -> 900 | G36: =G14*Assumptions!$F$37 -> 900 | H36: =H14*Assumptions!$F$37 -> 900 | I36: =I14*Assumptions!$F$37 -> 900 | J36: =J14*Assumptions!$F$37 -> 900 | ... N36: =N14*Assumptions!$F$37 -> 900 | O36: =SUM(C36:N36) -> 10800
A37: Option 2 — offshore contracting / compliance | B37: Not in original brief | C37: =C14*Assumptions!$F$38 -> 400 | D37: =D14*Assumptions!$F$38 -> 400 | E37: =E14*Assumptions!$F$38 -> 400 | F37: =F14*Assumptions!$F$38 -> 400 | G37: =G14*Assumptions!$F$38 -> 400 | H37: =H14*Assumptions!$F$38 -> 400 | I37: =I14*Assumptions!$F$38 -> 400 | J37: =J14*Assumptions!$F$38 -> 400 | ... N37: =N14*Assumptions!$F$38 -> 400 | O37: =SUM(C37:N37) -> 4800
A38: TOTAL — MARKETING OPTION 2 | C38: =SUM(C32:C37) -> 4775 | D38: =SUM(D32:D37) -> 4775 | E38: =SUM(E32:E37) -> 4775 | F38: =SUM(F32:F37) -> 4775 | G38: =SUM(G32:G37) -> 4775 | H38: =SUM(H32:H37) -> 4775 | I38: =SUM(I32:I37) -> 4775 | J38: =SUM(J32:J37) -> 4775 | ... N38: =SUM(N32:N37) -> 4775 | O38: =SUM(C38:N38) -> 57300 | P38: =IF($O$87=0,0,$O38/$O$87) -> 0.080281558
A40: D. UNIT-ACQUISITION COMMISSION — the 2% per management, ongoing
A41: Trailing commission on signed units (2%) | B41: 2% of live units' revenue, every month | C41: =IF(Assumptions!$F$41=1,C11,C12)*Assumptions!$F$40 -> 0 | D41: =IF(Assumptions!$F$41=1,D11,D12)*Assumptions!$F$40 -> 615.6 | E41: =IF(Assumptions!$F$41=1,E11,E12)*Assumptions!$F$40 -> 1436.4 | F41: =IF(Assumptions!$F$41=1,F11,F12)*Assumptions!$F$40 -> 2462.4 | G41: =IF(Assumptions!$F$41=1,G11,G12)*Assumptions!$F$40 -> 3693.6 | H41: =IF(Assumptions!$F$41=1,H11,H12)*Assumptions!$F$40 -> 4924.8 | I41: =IF(Assumptions!$F$41=1,I11,I12)*Assumptions!$F$40 -> 6361.2 | J41: =IF(Assumptions!$F$41=1,J11,J12)*Assumptions!$F$40 -> 7797.6 | ... N41: =IF(Assumptions!$F$41=1,N11,N12)*Assumptions!$F$40 -> 14569.2 | O41: =SUM(C41:N41) -> 75103.2
A42: TOTAL COMMISSION | C42: =SUM(C41:C41) -> 0 | D42: =SUM(D41:D41) -> 615.6 | E42: =SUM(E41:E41) -> 1436.4 | F42: =SUM(F41:F41) -> 2462.4 | G42: =SUM(G41:G41) -> 3693.6 | H42: =SUM(H41:H41) -> 4924.8 | I42: =SUM(I41:I41) -> 6361.2 | J42: =SUM(J41:J41) -> 7797.6 | ... N42: =SUM(N41:N41) -> 14569.2 | O42: =SUM(C42:N42) -> 75103.2 | P42: =IF($O$87=0,0,$O42/$O$87) -> 0.10522516
A44: E. TECHNOLOGY, PLATFORM & AI
A45: PMS / channel manager licence | B45: Per live unit | C45: =C9*Assumptions!$F$43 -> 0 | D45: =D9*Assumptions!$F$43 -> 225 | E45: =E9*Assumptions!$F$43 -> 525 | F45: =F9*Assumptions!$F$43 -> 900 | G45: =G9*Assumptions!$F$43 -> 1350 | H45: =H9*Assumptions!$F$43 -> 1800 | I45: =I9*Assumptions!$F$43 -> 2325 | J45: =J9*Assumptions!$F$43 -> 2850 | ... N45: =N9*Assumptions!$F$43 -> 5325 | O45: =SUM(C45:N45) -> 27450
A46: Dynamic pricing tool | B46: Per live unit | C46: =C9*Assumptions!$F$44 -> 0 | D46: =D9*Assumptions!$F$44 -> 96 | E46: =E9*Assumptions!$F$44 -> 224 | F46: =F9*Assumptions!$F$44 -> 384 | G46: =G9*Assumptions!$F$44 -> 576 | H46: =H9*Assumptions!$F$44 -> 768 | I46: =I9*Assumptions!$F$44 -> 992 | J46: =J9*Assumptions!$F$44 -> 1216 | ... N46: =N9*Assumptions!$F$44 -> 2272 | O46: =SUM(C46:N46) -> 11712
A47: Smart-lock / access platform | B47: Per live unit | C47: =C9*Assumptions!$F$45 -> 0 | D47: =D9*Assumptions!$F$45 -> 54 | E47: =E9*Assumptions!$F$45 -> 126 | F47: =F9*Assumptions!$F$45 -> 216 | G47: =G9*Assumptions!$F$45 -> 324 | H47: =H9*Assumptions!$F$45 -> 432 | I47: =I9*Assumptions!$F$45 -> 558 | J47: =J9*Assumptions!$F$45 -> 684 | ... N47: =N9*Assumptions!$F$45 -> 1278 | O47: =SUM(C47:N47) -> 6588
A48: AI subscriptions | B48: Per management — see 'AI Subscriptions' tab | C48: =Assumptions!$F$46 -> 1318.4275 | D48: =Assumptions!$F$46 -> 1318.4275 | E48: =Assumptions!$F$46 -> 1318.4275 | F48: =Assumptions!$F$46 -> 1318.4275 | G48: =Assumptions!$F$46 -> 1318.4275 | H48: =Assumptions!$F$46 -> 1318.4275 | I48: =Assumptions!$F$46 -> 1318.4275 | J48: =Assumptions!$F$46 -> 1318.4275 | ... N48: =Assumptions!$F$46 -> 1318.4275 | O48: =SUM(C48:N48) -> 15821.13
A49: Google Workspace & business email | C49: =Assumptions!$F$47 -> 150 | D49: =Assumptions!$F$47 -> 150 | E49: =Assumptions!$F$47 -> 150 | F49: =Assumptions!$F$47 -> 150 | G49: =Assumptions!$F$47 -> 150 | H49: =Assumptions!$F$47 -> 150 | I49: =Assumptions!$F$47 -> 150 | J49: =Assumptions!$F$47 -> 150 | ... N49: =Assumptions!$F$47 -> 150 | O49: =SUM(C49:N49) -> 1800
A50: Accounting software | C50: =Assumptions!$F$48 -> 160 | D50: =Assumptions!$F$48 -> 160 | E50: =Assumptions!$F$48 -> 160 | F50: =Assumptions!$F$48 -> 160 | G50: =Assumptions!$F$48 -> 160 | H50: =Assumptions!$F$48 -> 160 | I50: =Assumptions!$F$48 -> 160 | J50: =Assumptions!$F$48 -> 160 | ... N50: =Assumptions!$F$48 -> 160 | O50: =SUM(C50:N50) -> 1920
A51: Website hosting & direct booking engine | C51: =Assumptions!$F$49 -> 190 | D51: =Assumptions!$F$49 -> 190 | E51: =Assumptions!$F$49 -> 190 | F51: =Assumptions!$F$49 -> 190 | G51: =Assumptions!$F$49 -> 190 | H51: =Assumptions!$F$49 -> 190 | I51: =Assumptions!$F$49 -> 190 | J51: =Assumptions!$F$49 -> 190 | ... N51: =Assumptions!$F$49 -> 190 | O51: =SUM(C51:N51) -> 2280
A52: VoIP, WhatsApp Business API & guest line | B52: 24/7 support promise | C52: =Assumptions!$F$50 -> 230 | D52: =Assumptions!$F$50 -> 230 | E52: =Assumptions!$F$50 -> 230 | F52: =Assumptions!$F$50 -> 230 | G52: =Assumptions!$F$50 -> 230 | H52: =Assumptions!$F$50 -> 230 | I52: =Assumptions!$F$50 -> 230 | J52: =Assumptions!$F$50 -> 230 | ... N52: =Assumptions!$F$50 -> 230 | O52: =SUM(C52:N52) -> 2760
A53: TOTAL TECHNOLOGY & AI | C53: =SUM(C45:C52) -> 2048.4275 | D53: =SUM(D45:D52) -> 2423.4275 | E53: =SUM(E45:E52) -> 2923.4275 | F53: =SUM(F45:F52) -> 3548.4275 | G53: =SUM(G45:G52) -> 4298.4275 | H53: =SUM(H45:H52) -> 5048.4275 | I53: =SUM(I45:I52) -> 5923.4275 | J53: =SUM(J45:J52) -> 6798.4275 | ... N53: =SUM(N45:N52) -> 10923.427 | O53: =SUM(C53:N53) -> 70331.13 | P53: =IF($O$87=0,0,$O53/$O$87) -> 0.09853914
A55: F. UNIT OPERATIONS — variable with portfolio size
A56: DET holiday-home permit renewals (accrual) | B56: Per live unit, 1/12 of annual | C56: =C9*Assumptions!$F$52/12 -> 0 | D56: =D9*Assumptions!$F$52/12 -> 380 | E56: =E9*Assumptions!$F$52/12 -> 886.66667 | F56: =F9*Assumptions!$F$52/12 -> 1520 | G56: =G9*Assumptions!$F$52/12 -> 2280 | H56: =H9*Assumptions!$F$52/12 -> 3040 | I56: =I9*Assumptions!$F$52/12 -> 3926.6667 | J56: =J9*Assumptions!$F$52/12 -> 4813.3333 | ... N56: =N9*Assumptions!$F$52/12 -> 8993.3333 | O56: =SUM(C56:N56) -> 46360
A57: Housekeeping & laundry — net of guest recharge | B57: Per live unit | C57: =C9*Assumptions!$F$53 -> 0 | D57: =D9*Assumptions!$F$53 -> 540 | E57: =E9*Assumptions!$F$53 -> 1260 | F57: =F9*Assumptions!$F$53 -> 2160 | G57: =G9*Assumptions!$F$53 -> 3240 | H57: =H9*Assumptions!$F$53 -> 4320 | I57: =I9*Assumptions!$F$53 -> 5580 | J57: =J9*Assumptions!$F$53 -> 6840 | ... N57: =N9*Assumptions!$F$53 -> 12780 | O57: =SUM(C57:N57) -> 65880
A58: Guest consumables & amenities | B58: Per live unit | C58: =C9*Assumptions!$F$54 -> 0 | D58: =D9*Assumptions!$F$54 -> 300 | E58: =E9*Assumptions!$F$54 -> 700 | F58: =F9*Assumptions!$F$54 -> 1200 | G58: =G9*Assumptions!$F$54 -> 1800 | H58: =H9*Assumptions!$F$54 -> 2400 | I58: =I9*Assumptions!$F$54 -> 3100 | J58: =J9*Assumptions!$F$54 -> 3800 | ... N58: =N9*Assumptions!$F$54 -> 7100 | O58: =SUM(C58:N58) -> 36600
A59: Maintenance coordination & petty repairs | B59: Per live unit | C59: =C9*Assumptions!$F$55 -> 0 | D59: =D9*Assumptions!$F$55 -> 270 | E59: =E9*Assumptions!$F$55 -> 630 | F59: =F9*Assumptions!$F$55 -> 1080 | G59: =G9*Assumptions!$F$55 -> 1620 | H59: =H9*Assumptions!$F$55 -> 2160 | I59: =I9*Assumptions!$F$55 -> 2790 | J59: =J9*Assumptions!$F$55 -> 3420 | ... N59: =N9*Assumptions!$F$55 -> 6390 | O59: =SUM(C59:N59) -> 32940
A60: Linen & towel replacement | B60: Per live unit | C60: =C9*Assumptions!$F$56 -> 0 | D60: =D9*Assumptions!$F$56 -> 120 | E60: =E9*Assumptions!$F$56 -> 280 | F60: =F9*Assumptions!$F$56 -> 480 | G60: =G9*Assumptions!$F$56 -> 720 | H60: =H9*Assumptions!$F$56 -> 960 | I60: =I9*Assumptions!$F$56 -> 1240 | J60: =J9*Assumptions!$F$56 -> 1520 | ... N60: =N9*Assumptions!$F$56 -> 2840 | O60: =SUM(C60:N60) -> 14640
A61: TOTAL UNIT OPERATIONS | C61: =SUM(C56:C60) -> 0 | D61: =SUM(D56:D60) -> 1610 | E61: =SUM(E56:E60) -> 3756.6667 | F61: =SUM(F56:F60) -> 6440 | G61: =SUM(G56:G60) -> 9660 | H61: =SUM(H56:H60) -> 12880 | I61: =SUM(I56:I60) -> 16636.667 | J61: =SUM(J56:J60) -> 20393.333 | ... N61: =SUM(N56:N60) -> 38103.333 | O61: =SUM(C61:N61) -> 196420 | P61: =IF($O$87=0,0,$O61/$O$87) -> 0.27519902
A63: G. OFFICE & ADMINISTRATION — DUBAI
A64: Office rent / registered address | C64: =Assumptions!$F$58 -> 2500 | D64: =Assumptions!$F$58 -> 2500 | E64: =Assumptions!$F$58 -> 2500 | F64: =Assumptions!$F$58 -> 2500 | G64: =Assumptions!$F$58 -> 2500 | H64: =Assumptions!$F$58 -> 2500 | I64: =Assumptions!$F$58 -> 2500 | J64: =Assumptions!$F$58 -> 2500 | ... N64: =Assumptions!$F$58 -> 2500 | O64: =SUM(C64:N64) -> 30000
A65: Office DEWA, internet & chiller | C65: =Assumptions!$F$59 -> 520 | D65: =Assumptions!$F$59 -> 520 | E65: =Assumptions!$F$59 -> 520 | F65: =Assumptions!$F$59 -> 520 | G65: =Assumptions!$F$59 -> 520 | H65: =Assumptions!$F$59 -> 520 | I65: =Assumptions!$F$59 -> 520 | J65: =Assumptions!$F$59 -> 520 | ... N65: =Assumptions!$F$59 -> 520 | O65: =SUM(C65:N65) -> 6240
A66: Mobile & telephone | C66: =Assumptions!$F$60 -> 260 | D66: =Assumptions!$F$60 -> 260 | E66: =Assumptions!$F$60 -> 260 | F66: =Assumptions!$F$60 -> 260 | G66: =Assumptions!$F$60 -> 260 | H66: =Assumptions!$F$60 -> 260 | I66: =Assumptions!$F$60 -> 260 | J66: =Assumptions!$F$60 -> 260 | ... N66: =Assumptions!$F$60 -> 260 | O66: =SUM(C66:N66) -> 3120
A67: Transport, fuel, Salik & parking | C67: =Assumptions!$F$61 -> 1100 | D67: =Assumptions!$F$61 -> 1100 | E67: =Assumptions!$F$61 -> 1100 | F67: =Assumptions!$F$61 -> 1100 | G67: =Assumptions!$F$61 -> 1100 | H67: =Assumptions!$F$61 -> 1100 | I67: =Assumptions!$F$61 -> 1100 | J67: =Assumptions!$F$61 -> 1100 | ... N67: =Assumptions!$F$61 -> 1100 | O67: =SUM(C67:N67) -> 13200
A68: Office consumables, printing & courier | C68: =Assumptions!$F$62 -> 200 | D68: =Assumptions!$F$62 -> 200 | E68: =Assumptions!$F$62 -> 200 | F68: =Assumptions!$F$62 -> 200 | G68: =Assumptions!$F$62 -> 200 | H68: =Assumptions!$F$62 -> 200 | I68: =Assumptions!$F$62 -> 200 | J68: =Assumptions!$F$62 -> 200 | ... N68: =Assumptions!$F$62 -> 200 | O68: =SUM(C68:N68) -> 2400
A69: Bank charges & account maintenance | C69: =Assumptions!$F$63 -> 175 | D69: =Assumptions!$F$63 -> 175 | E69: =Assumptions!$F$63 -> 175 | F69: =Assumptions!$F$63 -> 175 | G69: =Assumptions!$F$63 -> 175 | H69: =Assumptions!$F$63 -> 175 | I69: =Assumptions!$F$63 -> 175 | J69: =Assumptions!$F$63 -> 175 | ... N69: =Assumptions!$F$63 -> 175 | O69: =SUM(C69:N69) -> 2100
A70: Payment gateway / OTA payout fees | B70: % of gross collections | C70: =C11*Assumptions!$F$64 -> 0 | D70: =D11*Assumptions!$F$64 -> 800.28 | E70: =E11*Assumptions!$F$64 -> 1867.32 | F70: =F11*Assumptions!$F$64 -> 3201.12 | G70: =G11*Assumptions!$F$64 -> 4801.68 | H70: =H11*Assumptions!$F$64 -> 6402.24 | I70: =I11*Assumptions!$F$64 -> 8269.56 | J70: =J11*Assumptions!$F$64 -> 10136.88 | ... N70: =N11*Assumptions!$F$64 -> 18939.96 | O70: =SUM(C70:N70) -> 97634.16
A71: TOTAL OFFICE & ADMIN | C71: =SUM(C64:C70) -> 4755 | D71: =SUM(D64:D70) -> 5555.28 | E71: =SUM(E64:E70) -> 6622.32 | F71: =SUM(F64:F70) -> 7956.12 | G71: =SUM(G64:G70) -> 9556.68 | H71: =SUM(H64:H70) -> 11157.24 | I71: =SUM(I64:I70) -> 13024.56 | J71: =SUM(J64:J70) -> 14891.88 | ... N71: =SUM(N64:N70) -> 23694.96 | O71: =SUM(C71:N71) -> 154694.16 | P71: =IF($O$87=0,0,$O71/$O$87) -> 0.21673801
A73: H. PROFESSIONAL, COMPLIANCE & INSURANCE
A74: Bookkeeping & management accounts | C74: =Assumptions!$F$66 -> 900 | D74: =Assumptions!$F$66 -> 900 | E74: =Assumptions!$F$66 -> 900 | F74: =Assumptions!$F$66 -> 900 | G74: =Assumptions!$F$66 -> 900 | H74: =Assumptions!$F$66 -> 900 | I74: =Assumptions!$F$66 -> 900 | J74: =Assumptions!$F$66 -> 900 | ... N74: =Assumptions!$F$66 -> 900 | O74: =SUM(C74:N74) -> 10800
A75: VAT return preparation & filing | B75: Quarterly — M3, M6, M9, M12 | C75: =IF(MOD(C6,3)=0,Assumptions!$F$67,0) -> 0 | D75: =IF(MOD(D6,3)=0,Assumptions!$F$67,0) -> 0 | E75: =IF(MOD(E6,3)=0,Assumptions!$F$67,0) -> 700 | F75: =IF(MOD(F6,3)=0,Assumptions!$F$67,0) -> 0 | G75: =IF(MOD(G6,3)=0,Assumptions!$F$67,0) -> 0 | H75: =IF(MOD(H6,3)=0,Assumptions!$F$67,0) -> 700 | I75: =IF(MOD(I6,3)=0,Assumptions!$F$67,0) -> 0 | J75: =IF(MOD(J6,3)=0,Assumptions!$F$67,0) -> 0 | ... N75: =IF(MOD(N6,3)=0,Assumptions!$F$67,0) -> 700 | O75: =SUM(C75:N75) -> 2800
A76: Corporate Tax compliance (accrual) | B76: 1/12 of annual | C76: =Assumptions!$F$68/12 -> 333.33333 | D76: =Assumptions!$F$68/12 -> 333.33333 | E76: =Assumptions!$F$68/12 -> 333.33333 | F76: =Assumptions!$F$68/12 -> 333.33333 | G76: =Assumptions!$F$68/12 -> 333.33333 | H76: =Assumptions!$F$68/12 -> 333.33333 | I76: =Assumptions!$F$68/12 -> 333.33333 | J76: =Assumptions!$F$68/12 -> 333.33333 | ... N76: =Assumptions!$F$68/12 -> 333.33333 | O76: =SUM(C76:N76) -> 4000
A77: External audit (accrual) | B77: 1/12 of annual | C77: =Assumptions!$F$69/12 -> 500 | D77: =Assumptions!$F$69/12 -> 500 | E77: =Assumptions!$F$69/12 -> 500 | F77: =Assumptions!$F$69/12 -> 500 | G77: =Assumptions!$F$69/12 -> 500 | H77: =Assumptions!$F$69/12 -> 500 | I77: =Assumptions!$F$69/12 -> 500 | J77: =Assumptions!$F$69/12 -> 500 | ... N77: =Assumptions!$F$69/12 -> 500 | O77: =SUM(C77:N77) -> 6000
A78: PRO / government liaison (accrual) | B78: 1/12 of annual | C78: =Assumptions!$F$70/12 -> 233.33333 | D78: =Assumptions!$F$70/12 -> 233.33333 | E78: =Assumptions!$F$70/12 -> 233.33333 | F78: =Assumptions!$F$70/12 -> 233.33333 | G78: =Assumptions!$F$70/12 -> 233.33333 | H78: =Assumptions!$F$70/12 -> 233.33333 | I78: =Assumptions!$F$70/12 -> 233.33333 | J78: =Assumptions!$F$70/12 -> 233.33333 | ... N78: =Assumptions!$F$70/12 -> 233.33333 | O78: =SUM(C78:N78) -> 2800
A79: Trade licence & DET permit renewal (accrual) | B79: 1/12 of annual | C79: =Assumptions!$F$71/12 -> 1583.3333 | D79: =Assumptions!$F$71/12 -> 1583.3333 | E79: =Assumptions!$F$71/12 -> 1583.3333 | F79: =Assumptions!$F$71/12 -> 1583.3333 | G79: =Assumptions!$F$71/12 -> 1583.3333 | H79: =Assumptions!$F$71/12 -> 1583.3333 | I79: =Assumptions!$F$71/12 -> 1583.3333 | J79: =Assumptions!$F$71/12 -> 1583.3333 | ... N79: =Assumptions!$F$71/12 -> 1583.3333 | O79: =SUM(C79:N79) -> 19000
A80: Public liability & PI insurance (accrual) | B80: 1/12 of annual | C80: =Assumptions!$F$72/12 -> 458.33333 | D80: =Assumptions!$F$72/12 -> 458.33333 | E80: =Assumptions!$F$72/12 -> 458.33333 | F80: =Assumptions!$F$72/12 -> 458.33333 | G80: =Assumptions!$F$72/12 -> 458.33333 | H80: =Assumptions!$F$72/12 -> 458.33333 | I80: =Assumptions!$F$72/12 -> 458.33333 | J80: =Assumptions!$F$72/12 -> 458.33333 | ... N80: =Assumptions!$F$72/12 -> 458.33333 | O80: =SUM(C80:N80) -> 5500
A81: Legal, contracts & disputes (accrual) | B81: 1/12 of annual | C81: =Assumptions!$F$73/12 -> 250 | D81: =Assumptions!$F$73/12 -> 250 | E81: =Assumptions!$F$73/12 -> 250 | F81: =Assumptions!$F$73/12 -> 250 | G81: =Assumptions!$F$73/12 -> 250 | H81: =Assumptions!$F$73/12 -> 250 | I81: =Assumptions!$F$73/12 -> 250 | J81: =Assumptions!$F$73/12 -> 250 | ... N81: =Assumptions!$F$73/12 -> 250 | O81: =SUM(C81:N81) -> 3000
A82: TOTAL PROFESSIONAL & COMPLIANCE | C82: =SUM(C74:C81) -> 4258.3333 | D82: =SUM(D74:D81) -> 4258.3333 | E82: =SUM(E74:E81) -> 4958.3333 | F82: =SUM(F74:F81) -> 4258.3333 | G82: =SUM(G74:G81) -> 4258.3333 | H82: =SUM(H74:H81) -> 4958.3333 | I82: =SUM(I74:I81) -> 4258.3333 | J82: =SUM(J74:J81) -> 4258.3333 | ... N82: =SUM(N74:N81) -> 4958.3333 | O82: =SUM(C82:N82) -> 53900 | P82: =IF($O$87=0,0,$O82/$O$87) -> 0.075517906
A84: TOTAL OPERATING EXPENDITURE
A85: OPEX before contingency | C85: =C22+C29+C38+C42+C53+C61+C71+C82 -> 23285.761 | D85: =D22+D29+D38+D42+D53+D61+D71+D82 -> 26686.641 | E85: =E22+E29+E38+E42+E53+E61+E71+E82 -> 28041.147 | F85: =F22+F29+F38+F42+F53+F61+F71+F82 -> 33009.281 | G85: =G22+G29+G38+G42+G53+G61+G71+G82 -> 39811.041 | H85: =H22+H29+H38+H42+H53+H61+H71+H82 -> 47312.801 | I85: =I22+I29+I38+I42+I53+I61+I71+I82 -> 54548.188 | J85: =J22+J29+J38+J42+J53+J61+J71+J82 -> 66052.574 | ... N85: =N22+N29+N38+N42+N53+N61+N71+N82 -> 107731.25 | O85: =SUM(C85:N85) -> 679750.49
A86: Contingency | B86: % of OPEX | C86: =C85*Assumptions!$F$75 -> 1164.288 | D86: =D85*Assumptions!$F$75 -> 1334.332 | E86: =E85*Assumptions!$F$75 -> 1402.0574 | F86: =F85*Assumptions!$F$75 -> 1650.464 | G86: =G85*Assumptions!$F$75 -> 1990.552 | H86: =H85*Assumptions!$F$75 -> 2365.64 | I86: =I85*Assumptions!$F$75 -> 2727.4094 | J86: =J85*Assumptions!$F$75 -> 3302.6287 | ... N86: =N85*Assumptions!$F$75 -> 5386.5627 | O86: =SUM(C86:N86) -> 33987.524
A87: TOTAL OPEX | C87: =C85+C86 -> 24450.049 | D87: =D85+D86 -> 28020.973 | E87: =E85+E86 -> 29443.205 | F87: =F85+F86 -> 34659.745 | G87: =G85+G86 -> 41801.593 | H87: =H85+H86 -> 49678.441 | I87: =I85+I86 -> 57275.597 | J87: =J85+J86 -> 69355.203 | ... N87: =N85+N86 -> 113117.82 | O87: =SUM(C87:N87) -> 713738.01
A89: SANITY CHECK — does the business cover its own costs?
A90: Orizuru revenue (management fees) | B90: From drivers | C90: =C12 -> 0 | D90: =D12 -> 6156 | E90: =E12 -> 14364 | F90: =F12 -> 24624 | G90: =G12 -> 36936 | H90: =H12 -> 49248 | I90: =I12 -> 63612 | J90: =J12 -> 77976 | ... N90: =N12 -> 145692 | O90: =SUM(C90:N90) -> 751032
A91: Total OPEX | C91: =C87 -> 24450.049 | D91: =D87 -> 28020.973 | E91: =E87 -> 29443.205 | F91: =F87 -> 34659.745 | G91: =G87 -> 41801.593 | H91: =H87 -> 49678.441 | I91: =I87 -> 57275.597 | J91: =J87 -> 69355.203 | ... N91: =N87 -> 113117.82 | O91: =SUM(C91:N91) -> 713738.01
A92: Operating surplus / (deficit) before tax & depreciation | B92: Revenue less OPEX | C92: =C90-C91 -> -24450.049 | D92: =D90-D91 -> -21864.973 | E92: =E90-E91 -> -15079.205 | F92: =F90-F91 -> -10035.745 | G92: =G90-G91 -> -4865.5929 | H92: =H90-H91 -> -430.44088 | I92: =I90-I91 -> 6336.4031 | J92: =J90-J91 -> 8620.7971 | ... N92: =N90-N91 -> 32574.183 | O92: =SUM(C92:N92) -> 37293.986
A93: Cumulative operating cash position | B93: Running | C93: =C92 -> -24450.049 | D93: =C93+D92 -> -46315.022 | E93: =D93+E92 -> -61394.227 | F93: =E93+F92 -> -71429.971 | G93: =F93+G92 -> -76295.564 | H93: =G93+H92 -> -76726.005 | I93: =H93+I92 -> -70389.602 | J93: =I93+J92 -> -61768.805 | K93: =J93+K92 -> -46989.472 | ... N93: =M93+N92 -> 37293.986 | O93: =N93 -> 37293.986
A94: OPEX as % of Orizuru revenue | B94: Lower is better | C94: =IF(C90=0,0,C91/C90) -> 0 | D94: =IF(D90=0,0,D91/D90) -> 4.551815 | E94: =IF(E90=0,0,E91/E90) -> 2.0497915 | F94: =IF(F90=0,0,F91/F90) -> 1.4075595 | G94: =IF(G90=0,0,G91/G90) -> 1.1317304 | H94: =IF(H90=0,0,H91/H90) -> 1.0087403 | I94: =IF(I90=0,0,I91/I90) -> 0.90038981 | J94: =IF(J90=0,0,J91/J90) -> 0.88944294 | ... O94: =IF(O90=0,0,O91/O90) -> 0.95034301
A95: OPEX per live unit | B95: Efficiency metric | C95: =IF(C9=0,0,C91/C9) -> 0 | D95: =IF(D9=0,0,D91/D9) -> 9340.3243 | E95: =IF(E9=0,0,E91/E9) -> 4206.1721 | F95: =IF(F9=0,0,F91/F9) -> 2888.3121 | G95: =IF(G9=0,0,G91/G9) -> 2322.3107 | H95: =IF(H9=0,0,H91/H9) -> 2069.935 | I95: =IF(I9=0,0,I91/I9) -> 1847.5999 | J95: =IF(J9=0,0,J91/J9) -> 1825.1369 | ... N95: =IF(N9=0,0,N91/N9) -> 1593.2087 | O95: =IF(N9=0,0,N91/N9) -> 1593.2087

Sheet Marketing Comparison
A1: MARKETING OPTION 1 vs OPTION 2 — THE MONTH-3 DECISION
A2: Both options run in parallel for Months 1–2 per management. This tab is what you use to pick one.
A4: HEAD-TO-HEAD, STEADY-STATE MONTHLY COST
A5: Component | B5: Option 1 — Fully online | C5: Option 2 — Remote office | D5: Difference | G5: Comment
A6: Team cost | B6: =Assumptions!$F$26*Assumptions!$F$27 -> 1800 | C6: =Assumptions!$F$32*Assumptions!$F$33 -> 1200 | D6: =B6-C6 -> 600 | G6: Option 2 buys roughly double the headcount for less money — offshore rates outside the UAE.
A7: Coworking / premises rent | B7: =0 -> 0 | C7: =Assumptions!$F$34 -> 1425 | D7: =B7-C7 -> -1425 | G7: Option 1 has no premises. This is the single line that erodes Option 2's labour-cost advantage.
A8: Local internet, utilities & equipment | B8: =0 -> 0 | C8: =Assumptions!$F$35 -> 350 | D8: =B8-C8 -> -350 | G8: Physical office overhead.
A9: On-site supervisor / team lead | B9: =Assumptions!$F$30 -> 300 | C9: =Assumptions!$F$36 -> 500 | D9: =B9-C9 -> -200 | G9: Option 1 needs light remote QA; Option 2 needs someone in the room.
A10: Digital ads & lead generation | B10: =Assumptions!$F$28 -> 1500 | C10: =Assumptions!$F$37 -> 900 | D10: =B10-C10 -> 600 | G10: Option 1 leans on paid leads; Option 2 leans on manual prospecting volume.
A11: Outreach tooling & CRM | B11: =Assumptions!$F$29 -> 280 | C11: =0 -> 0 | D11: =B11-C11 -> 280 | G11: Option 1 is tooling-dependent by design.
A12: Offshore contracting / compliance | B12: =0 -> 0 | C12: =Assumptions!$F$38 -> 400 | D12: =B12-C12 -> -400 | G12: Engaging staff outside the UAE needs a compliant route. Not in the original brief — flagged, not hidden.
A13: TOTAL FIXED MONTHLY COST | B13: =SUM(B6:B12) -> 3880 | C13: =SUM(C6:C12) -> 4775 | D13: =SUM(D6:D12) -> -895
A14: Headcount | B14: =Assumptions!$F$26 -> 3 | C14: =Assumptions!$F$32 -> 5 | D14: =B14-C14 -> -2 | G14: Both at 4 hours per day per management.
A15: Cost per head | B15: =IF(B14=0,0,B13/B14) -> 1293.3333 | C15: =IF(C14=0,0,C13/C14) -> 955 | D15: =B15-C15 -> 338.33333 | G15: All-in cost of one working person, including their share of premises and tooling. This is the number that actually decides it.
A17: BREAK-EVEN — how many units must each option sign to pay for itself?
A18: Orizuru revenue per live unit per month | B18: =Assumptions!$F$16 -> 2052 | G18: From the Assumptions tab.
A19: Units needed to cover the option's fixed cost | B19: =IF($B$18=0,0,B13/$B$18) -> 1.8908382 | C19: =IF($B$18=0,0,C13/$B$18) -> 2.3269981 | G19: Each option only has to sign this many units to wash its own face. Both numbers are small — which is why running both for two months is a cheap experiment, not a risk.
A21: COST OF THE 2-MONTH PARALLEL RUN
A22: Both options, Months 1–2 combined | B22: =(B13+C13)*Assumptions!$B$7 -> 17310 | G22: The total price of the experiment specified by management.
A23: Incremental cost vs running the cheaper option alone | B23: =(MAX(B13,C13))*Assumptions!$B$7 -> 9550 | G23: What the second option costs you on top. Judge the experiment against this, not the gross figure.
A24: Units the experiment must produce to justify itself | B24: =IF($B$18=0,0,B23/$B$18) -> 4.6539961 | G24: If the losing option signs at least this many units in two months, the experiment paid for itself regardless of which one you keep.
A26: WHAT TO MEASURE BEFORE YOU DECIDE IN MONTH 3
A27: • Units signed per option — the only metric that ultimately matters.
A28: • Cost per signed unit = the option's 2-month cost / units it signed. Compare directly.
A29: • Owner meetings booked per person per week — tells you whether the difference is effort or conversion.
A30: • Lead-to-meeting and meeting-to-signature conversion rates, tracked separately per option.
A31: • Quality of units signed: a team that signs cheap studios in weak buildings is not outperforming.
A32: • Attrition and reliability — Option 2's larger offshore team carries more people risk.
A33: • Language and time-zone fit with Dubai property owners. Under-weighted and it decides more deals than price does.
A35: READ-ACROSS
A36: • Option 2 typically wins on raw cost per head even after paying coworking rent, because it buys 4–6 people for roughly what 2–4 cost online. Its risk is not cost — it is supervision and consistency.
A37: • Option 1's real cost is the ads budget, not the salaries. Strip the ad spend out and it looks cheap, but a fully-online team with no lead flow signs nothing.
A38: • The 2% trailing commission applies identically to both options, so it does not affect the choice — but it does mean marketing cost keeps growing with the portfolio long after the team is fixed. See the OPEX Monthly tab.
A39: • Whatever you choose, the decision should be made on cost per SIGNED UNIT, not on total spend.

Sheet AI Subscriptions
A1: AI SUBSCRIPTIONS — DETAIL
A2: Specified by management. Feeds the 'AI subscriptions' line in the OPEX model. USD converted at the pegged AED rate.
A4: USD/AED peg | B4: 3.6725 | C4: AED is pegged to USD at 3.6725. Fixed, so no FX risk on these subscriptions.
A6: Tool | B6: Plan | C6: Seats | D6: Price/seat (USD, monthly) | E6: Monthly cost (AED) | F6: Annual cost (AED) | G6: What it does for Orizuru
A7: Claude | B7: Max (5x) | C7: 1 | D7: 100 | E7: =C7*D7*$B$4 -> 367.25 | F7: =E7*12 -> 4407 | G7: Core workhorse: owner proposals, management contracts, DET compliance drafting, financial reporting, guest-comms tone-of-voice.
A8: Claude | B8: Pro | C8: 2 | D8: 20 | E8: =C8*D8*$B$4 -> 146.9 | F8: =E8*12 -> 1762.8 | G8: Seats for the operations staff member and the marketing team lead.
A9: ChatGPT | B9: Business | C9: 2 | D9: 25 | E9: =C9*D9*$B$4 -> 183.625 | F9: =E9*12 -> 2203.5 | G9: Second-opinion model plus image generation for listing and social content.
A10: Google Gemini | B10: AI Pro (via Workspace) | C10: 2 | D10: 20 | E10: =C10*D10*$B$4 -> 146.9 | F10: =E10*12 -> 1762.8 | G10: Long-context document review and Sheets/Docs automation for owner reporting.
A11: Perplexity | B11: Pro | C11: 1 | D11: 20 | E11: =C11*D11*$B$4 -> 73.45 | F11: =E11*12 -> 881.4 | G11: Live comparable-rate research: what competing units in the same tower are charging tonight.
A12: Canva | B12: Pro / Teams | C12: 2 | D12: 15 | E12: =C12*D12*$B$4 -> 110.175 | F12: =E12*12 -> 1322.1 | G12: Listing graphics, owner pitch decks, social content at volume without a designer.
A13: PMS AI guest-messaging add-on | B13: Per-property tier | C13: 1 | D13: 49 | E13: =C13*D13*$B$4 -> 179.9525 | F13: =E13*12 -> 2159.43 | G13: Auto-responds to routine guest questions 24/7. Directly supports the 24/7 support promise in the Business Profile.
A14: AI transcription / meeting notes | B14: Standard | C14: 1 | D14: 18 | E14: =C14*D14*$B$4 -> 66.105 | F14: =E14*12 -> 793.26 | G14: Owner calls and site visits captured without manual note-taking.
A15: Buffer / social scheduling with AI | B15: Team | C15: 1 | D15: 12 | E15: =C15*D15*$B$4 -> 44.07 | F15: =E15*12 -> 528.84 | G15: Schedules the marketing team's output across channels.
A16: TOTAL — AI SUBSCRIPTIONS | E16: =SUM(E7:E15) -> 1318.4275 | F16: =SUM(F7:F15) -> 15821.13
A18: This is the Base case. In the OPEX model, the Low case assumes a trimmed stack (Claude Max + one assistant seat only) and the High case assumes the full stack plus additional seats as the marketing team scales. Edit seats and prices above and the Base figure flows straight through.
